{"in_reply_to_status_id_str":null,"in_reply_to_status_id":null,"created_at":"Thu Nov 30 12:05:07 +0000 2017","in_reply_to_user_id_str":null,"source":"<a href=\"http://instagram.com\" rel=\"nofollow\">Instagram<\/a>","retweet_count":0,"retweeted":false,"geo":{"coordinates":[41.363473,2.165827],"type":"Point"},"filter_level":"low","in_reply_to_screen_name":null,"is_quote_status":false,"id_str":"936204440763355136","in_reply_to_user_id":null,"favorite_count":0,"id":936204440763355136,"text":"#barcelona en Castillo de Montjuic https://t.co/1GvdI4vvI6","place":{"country_code":"ES","country":"España","full_name":"Barcelona, España","bounding_box":{"coordinates":[[[2.052477,41.317048],[2.052477,41.468266],[2.229978,41.468266],[2.229978,41.317048]]],"type":"Polygon"},"place_type":"city","name":"Barcelona","attributes":{},"id":"1a27537478dd8e38","url":"https://api.twitter.com/1.1/geo/id/1a27537478dd8e38.json"},"lang":"und","quote_count":0,"favorited":false,"possibly_sensitive":false,"coordinates":{"coordinates":[2.165827,41.363473],"type":"Point"},"truncated":false,"timestamp_ms":"1512043507172","reply_count":0,"entities":{"urls":[{"display_url":"instagram.com/p/BcHmV5DgrA2/","indices":[35,58],"expanded_url":"https://www.instagram.com/p/BcHmV5DgrA2/","url":"https://t.co/1GvdI4vvI6"}],"hashtags":[{"indices":[0,10],"text":"barcelona"}],"user_mentions":[],"symbols":[]},"contributors":null,"user":{"utc_offset":-10800,"friends_count":832,"profile_image_url_https":"https://pbs.twimg.com/profile_images/667800789742690304/RdWpKwgo_normal.jpg","listed_count":4,"profile_background_image_url":"http://pbs.twimg.com/profile_background_images/612917262/x3b0b7d1aa710f460acfddb79db3bb2a.jpg","default_profile_image":false,"favourites_count":220,"description":"no entiendo snapchat (estoy viejo)\nseguime en instagram http://instagram.com/maxiibarra92/","created_at":"Sat Jan 02 02:21:19 +0000 2010","is_translator":false,"profile_background_image_url_https":"https://pbs.twimg.com/profile_background_images/612917262/x3b0b7d1aa710f460acfddb79db3bb2a.jpg","protected":false,"screen_name":"maxiibarra","id_str":"101112813","profile_link_color":"1B95E0","translator_type":"none","id":101112813,"geo_enabled":true,"profile_background_color":"7A666A","lang":"es","profile_sidebar_border_color":"F1DEB1","profile_text_color":"E4A88F","verified":false,"profile_image_url":"http://pbs.twimg.com/profile_images/667800789742690304/RdWpKwgo_normal.jpg","time_zone":"Buenos Aires","url":"http://www.facebook.com/maxiibirra","contributors_enabled":false,"profile_background_tile":true,"profile_banner_url":"https://pbs.twimg.com/profile_banners/101112813/1348636123","statuses_count":2510,"follow_request_sent":null,"followers_count":503,"profile_use_background_image":true,"default_profile":false,"following":null,"name":"Maxi Ibarra","location":"Villa Constitucion, Santa Fe","profile_sidebar_fill_color":"EEC5A1","notifications":null}}