<?xml version='1.0' encoding='UTF-8'?>
<GateDocument version="3">
<!-- The document's features-->

<GateDocumentFeatures>
<Feature>
  <Name className="java.lang.String">gate.SourceURL</Name>
  <Value className="java.lang.String">file:/C:/Users/filip/AIW2017_P3_G3/data/json/936198268228382720.json</Value>
</Feature>
<Feature>
  <Name className="java.lang.String">MimeType</Name>
  <Value className="java.lang.String">text/x-json-twitter</Value>
</Feature>
<Feature>
  <Name className="java.lang.String">docNewLineType</Name>
  <Value className="java.lang.String"></Value>
</Feature>
</GateDocumentFeatures>
<!-- The document content area with serialized nodes -->

<TextWithNodes><Node id="0"/>No<Node id="2"/>?<Node id="3"/>?<Node id="4"/>?<Node id="5"/> <Node id="6"/>https://t.<Node id="16"/>co<Node id="18"/>/O6qt1o6hbW<Node id="29"/>
<Node id="30"/>
<Node id="31"/></TextWithNodes>
<!-- The default annotation set -->

<AnnotationSet>
<Annotation Id="0" Type="Tweet" StartNode="0" EndNode="29">
<Feature>
  <Name className="java.lang.String">quoted_status</Name>
  <Value className="gate.corpora.ObjectWrapper"><![CDATA[<?xml version='1.1'?><gate.corpora.ObjectWrapper><value class="gate.util.SimpleFeatureMapImpl" serialization="custom"><gate.util.SimpleMapImpl><default><capacity>48</capacity><count>26</count><theKeys><string>in_reply_to_status_id_str</string><string>in_reply_to_status_id</string><string>created_at</string><string>in_reply_to_user_id_str</string><string>source</string><string>retweet_count</string><string>retweeted</string><string>geo</string><string>filter_level</string><string>in_reply_to_screen_name</string><string>is_quote_status</string><string>id_str</string><string>in_reply_to_user_id</string><string>favorite_count</string><string>id</string><string>text</string><string>place</string><string>lang</string><string>quote_count</string><string>favorited</string><string>coordinates</string><string>truncated</string><string>reply_count</string><string>entities</string><string>contributors</string><string>user</string><null/><null/><null/><null/><null/><null/><null/><null/><null/><null/><null/><null/><null/><null/><null/><null/><null/><null/><null/><null/><null/><null/></theKeys><theValues><null/><null/><string>Sun Nov 19 05:29:12 +0000 2017</string><null/><string>&lt;a href="http://twitter.com/download/android" rel="nofollow">Twitter for Android&lt;/a></string><long>37</long><boolean>false</boolean><null/><string>low</string><null/><boolean>false</boolean><string>932118541817360384</string><null/><long>148</long><long>932118541817360384</long><string>Típico de las mujeres, cuando ven a otra mujer guapa y bien vestida ya piensan que es una puta. ¿Tengo o no tengo razón?</string><null/><string>es</string><long>69</long><boolean>false</boolean><null/><boolean>false</boolean><long>26</long><gate.util.SimpleFeatureMapImpl serialization="custom"><gate.util.SimpleMapImpl><default><capacity>6</capacity><count>4</count><theKeys><string>urls</string><string>hashtags</string><string>user_mentions</string><string>symbols</string><null/><null/></theKeys><theValues><list/><list/><list/><list/><null/><null/></theValues></default></gate.util.SimpleMapImpl></gate.util.SimpleFeatureMapImpl><null/><gate.util.SimpleFeatureMapImpl serialization="custom"><gate.util.SimpleMapImpl><default><capacity>48</capacity><count>39</count><theKeys><string>utc_offset</string><string>friends_count</string><string>profile_image_url_https</string><string>listed_count</string><string>profile_background_image_url</string><string>default_profile_image</string><string>favourites_count</string><string>description</string><string>created_at</string><string>is_translator</string><string>profile_background_image_url_https</string><string>protected</string><string>screen_name</string><string>id_str</string><string>profile_link_color</string><string>translator_type</string><string>id</string><string>geo_enabled</string><string>profile_background_color</string><string>lang</string><string>profile_sidebar_border_color</string><string>profile_text_color</string><string>verified</string><string>profile_image_url</string><string>time_zone</string><string>url</string><string>contributors_enabled</string><string>profile_background_tile</string><string>profile_banner_url</string><string>statuses_count</string><string>follow_request_sent</string><string>followers_count</string><string>profile_use_background_image</string><string>default_profile</string><string>following</string><string>name</string><string>location</string><string>profile_sidebar_fill_color</string><string>notifications</string><null/><null/><null/><null/><null/><null/><null/><null/><null/></theKeys><theValues><long>-21600</long><long>364</long><string>https://pbs.twimg.com/profile_images/928856197591056384/-dg1LvEP_normal.jpg</string><long>70</long><string>http://pbs.twimg.com/profile_background_images/623348163059957760/ZRR7l2X1.png</string><boolean>false</boolean><long>79796</long><string>Soy más sarcasmo que persona</string><string>Tue Sep 20 00:20:04 +0000 2011</string><boolean>true</boolean><string>https://pbs.twimg.com/profile_background_images/623348163059957760/ZRR7l2X1.png</string><boolean>false</boolean><string>SoyChuchoTec</string><string>376496514</string><string>1F98C7</string><string>badged</string><long>376496514</long><boolean>true</boolean><string>C6E2EE</string><string>es</string><string>FFFFFF</string><string>666666</string><boolean>false</boolean><string>http://pbs.twimg.com/profile_images/928856197591056384/-dg1LvEP_normal.jpg</string><string>Central Time (US &amp; Canada)</string><string>http://Instagram.com/SoyChuchoTec</string><boolean>false</boolean><boolean>true</boolean><string>https://pbs.twimg.com/profile_banners/376496514/1504514790</string><long>19380</long><null/><long>51205</long><boolean>true</boolean><boolean>false</boolean><null/><string>Chucho El Chido</string><string>Veracruz - México</string><string>252429</string><null/><null/><null/><null/><null/><null/><null/><null/><null/><null/></theValues></default></gate.util.SimpleMapImpl></gate.util.SimpleFeatureMapImpl><null/><null/><null/><null/><null/><null/><null/><null/><null/><null/><null/><null/><null/><null/><null/><null/><null/><null/><null/><null/><null/><null/></theValues></default></gate.util.SimpleMapImpl></value></gate.corpora.ObjectWrapper>]]></Value>
</Feature>
<Feature>
  <Name className="java.lang.String">created_at</Name>
  <Value className="java.lang.String">Thu Nov 30 11:40:35 +0000 2017</Value>
</Feature>
<Feature>
  <Name className="java.lang.String">source</Name>
  <Value className="java.lang.String">&lt;a href="http://twitter.com/download/android" rel="nofollow">Twitter for Android&lt;/a></Value>
</Feature>
<Feature>
  <Name className="java.lang.String">quoted_status_id</Name>
  <Value className="java.lang.Long">932118541817360384</Value>
</Feature>
<Feature>
  <Name className="java.lang.String">retweet_count</Name>
  <Value className="java.lang.Long">0</Value>
</Feature>
<Feature>
  <Name className="java.lang.String">retweeted</Name>
  <Value className="java.lang.Boolean">false</Value>
</Feature>
<Feature>
  <Name className="java.lang.String">filter_level</Name>
  <Value className="java.lang.String">low</Value>
</Feature>
<Feature>
  <Name className="java.lang.String">is_quote_status</Name>
  <Value className="java.lang.Boolean">true</Value>
</Feature>
<Feature>
  <Name className="java.lang.String">id_str</Name>
  <Value className="java.lang.String">936198268228382720</Value>
</Feature>
<Feature>
  <Name className="java.lang.String">favorite_count</Name>
  <Value className="java.lang.Long">0</Value>
</Feature>
<Feature>
  <Name className="java.lang.String">id</Name>
  <Value className="java.lang.Long">936198268228382720</Value>
</Feature>
<Feature>
  <Name className="java.lang.String">place</Name>
  <Value className="gate.corpora.ObjectWrapper"><![CDATA[<?xml version='1.1'?><gate.corpora.ObjectWrapper><value class="gate.util.SimpleFeatureMapImpl" serialization="custom"><gate.util.SimpleMapImpl><default><capacity>12</capacity><count>9</count><theKeys><string>country_code</string><string>country</string><string>full_name</string><string>bounding_box</string><string>place_type</string><string>name</string><string>attributes</string><string>id</string><string>url</string><null/><null/><null/></theKeys><theValues><string>ES</string><string>España</string><string>Barcelona, España</string><gate.util.SimpleFeatureMapImpl serialization="custom"><gate.util.SimpleMapImpl><default><capacity>3</capacity><count>2</count><theKeys><string>coordinates</string><string>type</string><null/></theKeys><theValues><list><list><list><double>2.052477</double><double>41.317048</double></list><list><double>2.052477</double><double>41.468266</double></list><list><double>2.229978</double><double>41.468266</double></list><list><double>2.229978</double><double>41.317048</double></list></list></list><string>Polygon</string><null/></theValues></default></gate.util.SimpleMapImpl></gate.util.SimpleFeatureMapImpl><string>city</string><string>Barcelona</string><gate.util.SimpleFeatureMapImpl serialization="custom"><gate.util.SimpleMapImpl><default><capacity>3</capacity><count>0</count><theKeys><null/><null/><null/></theKeys><theValues><null/><null/><null/></theValues></default></gate.util.SimpleMapImpl></gate.util.SimpleFeatureMapImpl><string>1a27537478dd8e38</string><string>https://api.twitter.com/1.1/geo/id/1a27537478dd8e38.json</string><null/><null/><null/></theValues></default></gate.util.SimpleMapImpl></value></gate.corpora.ObjectWrapper>]]></Value>
</Feature>
<Feature>
  <Name className="java.lang.String">lang</Name>
  <Value className="java.lang.String">english</Value>
</Feature>
<Feature>
  <Name className="java.lang.String">quote_count</Name>
  <Value className="java.lang.Long">0</Value>
</Feature>
<Feature>
  <Name className="java.lang.String">favorited</Name>
  <Value className="java.lang.Boolean">false</Value>
</Feature>
<Feature>
  <Name className="java.lang.String">possibly_sensitive</Name>
  <Value className="java.lang.Boolean">false</Value>
</Feature>
<Feature>
  <Name className="java.lang.String">truncated</Name>
  <Value className="java.lang.Boolean">false</Value>
</Feature>
<Feature>
  <Name className="java.lang.String">timestamp_ms</Name>
  <Value className="java.lang.String">1512042035525</Value>
</Feature>
<Feature>
  <Name className="java.lang.String">reply_count</Name>
  <Value className="java.lang.Long">0</Value>
</Feature>
<Feature>
  <Name className="java.lang.String">display_text_range</Name>
  <Value className="gate.corpora.ObjectWrapper"><![CDATA[<?xml version='1.1'?><gate.corpora.ObjectWrapper><value class="list"><long>0</long><long>5</long></value></gate.corpora.ObjectWrapper>]]></Value>
</Feature>
<Feature>
  <Name className="java.lang.String">quoted_status_id_str</Name>
  <Value className="java.lang.String">932118541817360384</Value>
</Feature>
<Feature>
  <Name className="java.lang.String">user</Name>
  <Value className="gate.corpora.ObjectWrapper"><![CDATA[<?xml version='1.1'?><gate.corpora.ObjectWrapper><value class="gate.util.SimpleFeatureMapImpl" serialization="custom"><gate.util.SimpleMapImpl><default><capacity>48</capacity><count>39</count><theKeys><string>utc_offset</string><string>friends_count</string><string>profile_image_url_https</string><string>listed_count</string><string>profile_background_image_url</string><string>default_profile_image</string><string>favourites_count</string><string>description</string><string>created_at</string><string>is_translator</string><string>profile_background_image_url_https</string><string>protected</string><string>screen_name</string><string>id_str</string><string>profile_link_color</string><string>translator_type</string><string>id</string><string>geo_enabled</string><string>profile_background_color</string><string>lang</string><string>profile_sidebar_border_color</string><string>profile_text_color</string><string>verified</string><string>profile_image_url</string><string>time_zone</string><string>url</string><string>contributors_enabled</string><string>profile_background_tile</string><string>profile_banner_url</string><string>statuses_count</string><string>follow_request_sent</string><string>followers_count</string><string>profile_use_background_image</string><string>default_profile</string><string>following</string><string>name</string><string>location</string><string>profile_sidebar_fill_color</string><string>notifications</string><null/><null/><null/><null/><null/><null/><null/><null/><null/></theKeys><theValues><long>3600</long><long>292</long><string>https://pbs.twimg.com/profile_images/926451428083879937/WotlKxEv_normal.jpg</string><long>5</long><string>http://pbs.twimg.com/profile_background_images/692422655362908160/sG4ULj6D.jpg</string><boolean>false</boolean><long>5018</long><string>Mare de Déu del brioix de mantega...</string><string>Sun Jul 05 18:57:13 +0000 2009</string><boolean>false</boolean><string>https://pbs.twimg.com/profile_background_images/692422655362908160/sG4ULj6D.jpg</string><boolean>false</boolean><string>Llesquins</string><string>53976096</string><string>F5ABB5</string><string>none</string><long>53976096</long><boolean>true</boolean><string>F5ABB5</string><string>es</string><string>000000</string><string>000000</string><boolean>false</boolean><string>http://pbs.twimg.com/profile_images/926451428083879937/WotlKxEv_normal.jpg</string><string>Madrid</string><string>http://samusa.tumblr.com</string><boolean>false</boolean><boolean>true</boolean><string>https://pbs.twimg.com/profile_banners/53976096/1506637573</string><long>71431</long><null/><long>131</long><boolean>true</boolean><boolean>false</boolean><null/><string>Ari 🎗️</string><string>Can Pixa, República Catalana</string><string>000000</string><null/><null/><null/><null/><null/><null/><null/><null/><null/><null/></theValues></default></gate.util.SimpleMapImpl></value></gate.corpora.ObjectWrapper>]]></Value>
</Feature>
</Annotation>
<Annotation Id="67" Type="Lookup" StartNode="16" EndNode="18">
<Feature>
  <Name className="java.lang.String">majorType</Name>
  <Value className="java.lang.String">country_code</Value>
</Feature>
</Annotation>
<Annotation Id="68" Type="Lookup" StartNode="16" EndNode="18">
<Feature>
  <Name className="java.lang.String">majorType</Name>
  <Value className="java.lang.String">url_key</Value>
</Feature>
</Annotation>
<Annotation Id="69" Type="Split" StartNode="2" EndNode="5">
<Feature>
  <Name className="java.lang.String">kind</Name>
  <Value className="java.lang.String">internal</Value>
</Feature>
</Annotation>
<Annotation Id="38" Type="Token" StartNode="0" EndNode="2">
<Feature>
  <Name className="java.lang.String">length</Name>
  <Value className="java.lang.String">2</Value>
</Feature>
<Feature>
  <Name className="java.lang.String">orth</Name>
  <Value className="java.lang.String">upperInitial</Value>
</Feature>
<Feature>
  <Name className="java.lang.String">string</Name>
  <Value className="java.lang.String">No</Value>
</Feature>
<Feature>
  <Name className="java.lang.String">category</Name>
  <Value className="java.lang.String">UH</Value>
</Feature>
<Feature>
  <Name className="java.lang.String">kind</Name>
  <Value className="java.lang.String">word</Value>
</Feature>
</Annotation>
<Annotation Id="70" Type="Split" StartNode="29" EndNode="31">
<Feature>
  <Name className="java.lang.String">kind</Name>
  <Value className="java.lang.String">external</Value>
</Feature>
</Annotation>
<Annotation Id="39" Type="Token" StartNode="2" EndNode="3">
<Feature>
  <Name className="java.lang.String">length</Name>
  <Value className="java.lang.String">1</Value>
</Feature>
<Feature>
  <Name className="java.lang.String">string</Name>
  <Value className="java.lang.String">?</Value>
</Feature>
<Feature>
  <Name className="java.lang.String">category</Name>
  <Value className="java.lang.String">.</Value>
</Feature>
<Feature>
  <Name className="java.lang.String">kind</Name>
  <Value className="java.lang.String">punctuation</Value>
</Feature>
</Annotation>
<Annotation Id="71" Type="Sentence" StartNode="0" EndNode="5">
</Annotation>
<Annotation Id="40" Type="Token" StartNode="3" EndNode="4">
<Feature>
  <Name className="java.lang.String">length</Name>
  <Value className="java.lang.String">1</Value>
</Feature>
<Feature>
  <Name className="java.lang.String">string</Name>
  <Value className="java.lang.String">?</Value>
</Feature>
<Feature>
  <Name className="java.lang.String">category</Name>
  <Value className="java.lang.String">UH</Value>
</Feature>
<Feature>
  <Name className="java.lang.String">kind</Name>
  <Value className="java.lang.String">punctuation</Value>
</Feature>
</Annotation>
<Annotation Id="72" Type="Sentence" StartNode="6" EndNode="29">
</Annotation>
<Annotation Id="41" Type="Token" StartNode="4" EndNode="5">
<Feature>
  <Name className="java.lang.String">length</Name>
  <Value className="java.lang.String">1</Value>
</Feature>
<Feature>
  <Name className="java.lang.String">string</Name>
  <Value className="java.lang.String">?</Value>
</Feature>
<Feature>
  <Name className="java.lang.String">category</Name>
  <Value className="java.lang.String">.</Value>
</Feature>
<Feature>
  <Name className="java.lang.String">kind</Name>
  <Value className="java.lang.String">punctuation</Value>
</Feature>
</Annotation>
<Annotation Id="73" Type="Upper" StartNode="0" EndNode="2">
<Feature>
  <Name className="java.lang.String">rule</Name>
  <Value className="java.lang.String">Upper</Value>
</Feature>
</Annotation>
<Annotation Id="42" Type="SpaceToken" StartNode="5" EndNode="6">
<Feature>
  <Name className="java.lang.String">string</Name>
  <Value className="java.lang.String"> </Value>
</Feature>
<Feature>
  <Name className="java.lang.String">length</Name>
  <Value className="java.lang.String">1</Value>
</Feature>
<Feature>
  <Name className="java.lang.String">kind</Name>
  <Value className="java.lang.String">space</Value>
</Feature>
</Annotation>
<Annotation Id="60" Type="Token" StartNode="6" EndNode="29">
<Feature>
  <Name className="java.lang.String">string</Name>
  <Value className="java.lang.String">https://t.co/O6qt1o6hbW</Value>
</Feature>
<Feature>
  <Name className="java.lang.String">kind</Name>
  <Value className="java.lang.String">URL</Value>
</Feature>
<Feature>
  <Name className="java.lang.String">temp_category</Name>
  <Value className="java.lang.String">NN</Value>
</Feature>
<Feature>
  <Name className="java.lang.String">length</Name>
  <Value className="java.lang.Long">23</Value>
</Feature>
<Feature>
  <Name className="java.lang.String">rule</Name>
  <Value className="java.lang.String">URL</Value>
</Feature>
<Feature>
  <Name className="java.lang.String">replaced</Name>
  <Value className="java.lang.Integer">15</Value>
</Feature>
<Feature>
  <Name className="java.lang.String">category</Name>
  <Value className="java.lang.String">UH</Value>
</Feature>
</Annotation>
<Annotation Id="61" Type="URL" StartNode="6" EndNode="29">
<Feature>
  <Name className="java.lang.String">string</Name>
  <Value className="java.lang.String">https://t.co/O6qt1o6hbW</Value>
</Feature>
<Feature>
  <Name className="java.lang.String">kind</Name>
  <Value className="java.lang.String">URL</Value>
</Feature>
<Feature>
  <Name className="java.lang.String">temp_category</Name>
  <Value className="java.lang.String">NN</Value>
</Feature>
<Feature>
  <Name className="java.lang.String">length</Name>
  <Value className="java.lang.Long">23</Value>
</Feature>
<Feature>
  <Name className="java.lang.String">rule</Name>
  <Value className="java.lang.String">URL</Value>
</Feature>
<Feature>
  <Name className="java.lang.String">replaced</Name>
  <Value className="java.lang.Integer">15</Value>
</Feature>
<Feature>
  <Name className="java.lang.String">category</Name>
  <Value className="java.lang.String">UH</Value>
</Feature>
</Annotation>
<Annotation Id="62" Type="SpaceToken" StartNode="29" EndNode="30">
<Feature>
  <Name className="java.lang.String">string</Name>
  <Value className="java.lang.String">
</Value>
</Feature>
<Feature>
  <Name className="java.lang.String">length</Name>
  <Value className="java.lang.String">1</Value>
</Feature>
<Feature>
  <Name className="java.lang.String">kind</Name>
  <Value className="java.lang.String">control</Value>
</Feature>
</Annotation>
<Annotation Id="63" Type="SpaceToken" StartNode="30" EndNode="31">
<Feature>
  <Name className="java.lang.String">string</Name>
  <Value className="java.lang.String">
</Value>
</Feature>
<Feature>
  <Name className="java.lang.String">length</Name>
  <Value className="java.lang.String">1</Value>
</Feature>
<Feature>
  <Name className="java.lang.String">kind</Name>
  <Value className="java.lang.String">control</Value>
</Feature>
</Annotation>
</AnnotationSet>

<!-- Named annotation set -->

<AnnotationSet Name="Original markups">
<Annotation Id="0" Type="Tweet" StartNode="0" EndNode="29">
<Feature>
  <Name className="java.lang.String">quoted_status</Name>
  <Value className="gate.corpora.ObjectWrapper"><![CDATA[<?xml version='1.1'?><gate.corpora.ObjectWrapper><value class="gate.util.SimpleFeatureMapImpl" serialization="custom"><gate.util.SimpleMapImpl><default><capacity>48</capacity><count>26</count><theKeys><string>in_reply_to_status_id_str</string><string>in_reply_to_status_id</string><string>created_at</string><string>in_reply_to_user_id_str</string><string>source</string><string>retweet_count</string><string>retweeted</string><string>geo</string><string>filter_level</string><string>in_reply_to_screen_name</string><string>is_quote_status</string><string>id_str</string><string>in_reply_to_user_id</string><string>favorite_count</string><string>id</string><string>text</string><string>place</string><string>lang</string><string>quote_count</string><string>favorited</string><string>coordinates</string><string>truncated</string><string>reply_count</string><string>entities</string><string>contributors</string><string>user</string><null/><null/><null/><null/><null/><null/><null/><null/><null/><null/><null/><null/><null/><null/><null/><null/><null/><null/><null/><null/><null/><null/></theKeys><theValues><null/><null/><string>Sun Nov 19 05:29:12 +0000 2017</string><null/><string>&lt;a href="http://twitter.com/download/android" rel="nofollow">Twitter for Android&lt;/a></string><long>37</long><boolean>false</boolean><null/><string>low</string><null/><boolean>false</boolean><string>932118541817360384</string><null/><long>148</long><long>932118541817360384</long><string>Típico de las mujeres, cuando ven a otra mujer guapa y bien vestida ya piensan que es una puta. ¿Tengo o no tengo razón?</string><null/><string>es</string><long>69</long><boolean>false</boolean><null/><boolean>false</boolean><long>26</long><gate.util.SimpleFeatureMapImpl serialization="custom"><gate.util.SimpleMapImpl><default><capacity>6</capacity><count>4</count><theKeys><string>urls</string><string>hashtags</string><string>user_mentions</string><string>symbols</string><null/><null/></theKeys><theValues><list/><list/><list/><list/><null/><null/></theValues></default></gate.util.SimpleMapImpl></gate.util.SimpleFeatureMapImpl><null/><gate.util.SimpleFeatureMapImpl serialization="custom"><gate.util.SimpleMapImpl><default><capacity>48</capacity><count>39</count><theKeys><string>utc_offset</string><string>friends_count</string><string>profile_image_url_https</string><string>listed_count</string><string>profile_background_image_url</string><string>default_profile_image</string><string>favourites_count</string><string>description</string><string>created_at</string><string>is_translator</string><string>profile_background_image_url_https</string><string>protected</string><string>screen_name</string><string>id_str</string><string>profile_link_color</string><string>translator_type</string><string>id</string><string>geo_enabled</string><string>profile_background_color</string><string>lang</string><string>profile_sidebar_border_color</string><string>profile_text_color</string><string>verified</string><string>profile_image_url</string><string>time_zone</string><string>url</string><string>contributors_enabled</string><string>profile_background_tile</string><string>profile_banner_url</string><string>statuses_count</string><string>follow_request_sent</string><string>followers_count</string><string>profile_use_background_image</string><string>default_profile</string><string>following</string><string>name</string><string>location</string><string>profile_sidebar_fill_color</string><string>notifications</string><null/><null/><null/><null/><null/><null/><null/><null/><null/></theKeys><theValues><long>-21600</long><long>364</long><string>https://pbs.twimg.com/profile_images/928856197591056384/-dg1LvEP_normal.jpg</string><long>70</long><string>http://pbs.twimg.com/profile_background_images/623348163059957760/ZRR7l2X1.png</string><boolean>false</boolean><long>79796</long><string>Soy más sarcasmo que persona</string><string>Tue Sep 20 00:20:04 +0000 2011</string><boolean>true</boolean><string>https://pbs.twimg.com/profile_background_images/623348163059957760/ZRR7l2X1.png</string><boolean>false</boolean><string>SoyChuchoTec</string><string>376496514</string><string>1F98C7</string><string>badged</string><long>376496514</long><boolean>true</boolean><string>C6E2EE</string><string>es</string><string>FFFFFF</string><string>666666</string><boolean>false</boolean><string>http://pbs.twimg.com/profile_images/928856197591056384/-dg1LvEP_normal.jpg</string><string>Central Time (US &amp; Canada)</string><string>http://Instagram.com/SoyChuchoTec</string><boolean>false</boolean><boolean>true</boolean><string>https://pbs.twimg.com/profile_banners/376496514/1504514790</string><long>19380</long><null/><long>51205</long><boolean>true</boolean><boolean>false</boolean><null/><string>Chucho El Chido</string><string>Veracruz - México</string><string>252429</string><null/><null/><null/><null/><null/><null/><null/><null/><null/><null/></theValues></default></gate.util.SimpleMapImpl></gate.util.SimpleFeatureMapImpl><null/><null/><null/><null/><null/><null/><null/><null/><null/><null/><null/><null/><null/><null/><null/><null/><null/><null/><null/><null/><null/><null/></theValues></default></gate.util.SimpleMapImpl></value></gate.corpora.ObjectWrapper>]]></Value>
</Feature>
<Feature>
  <Name className="java.lang.String">created_at</Name>
  <Value className="java.lang.String">Thu Nov 30 11:40:35 +0000 2017</Value>
</Feature>
<Feature>
  <Name className="java.lang.String">source</Name>
  <Value className="java.lang.String">&lt;a href="http://twitter.com/download/android" rel="nofollow">Twitter for Android&lt;/a></Value>
</Feature>
<Feature>
  <Name className="java.lang.String">quoted_status_id</Name>
  <Value className="java.lang.Long">932118541817360384</Value>
</Feature>
<Feature>
  <Name className="java.lang.String">retweet_count</Name>
  <Value className="java.lang.Long">0</Value>
</Feature>
<Feature>
  <Name className="java.lang.String">retweeted</Name>
  <Value className="java.lang.Boolean">false</Value>
</Feature>
<Feature>
  <Name className="java.lang.String">filter_level</Name>
  <Value className="java.lang.String">low</Value>
</Feature>
<Feature>
  <Name className="java.lang.String">is_quote_status</Name>
  <Value className="java.lang.Boolean">true</Value>
</Feature>
<Feature>
  <Name className="java.lang.String">id_str</Name>
  <Value className="java.lang.String">936198268228382720</Value>
</Feature>
<Feature>
  <Name className="java.lang.String">favorite_count</Name>
  <Value className="java.lang.Long">0</Value>
</Feature>
<Feature>
  <Name className="java.lang.String">id</Name>
  <Value className="java.lang.Long">936198268228382720</Value>
</Feature>
<Feature>
  <Name className="java.lang.String">place</Name>
  <Value className="gate.corpora.ObjectWrapper"><![CDATA[<?xml version='1.1'?><gate.corpora.ObjectWrapper><value class="gate.util.SimpleFeatureMapImpl" serialization="custom"><gate.util.SimpleMapImpl><default><capacity>12</capacity><count>9</count><theKeys><string>country_code</string><string>country</string><string>full_name</string><string>bounding_box</string><string>place_type</string><string>name</string><string>attributes</string><string>id</string><string>url</string><null/><null/><null/></theKeys><theValues><string>ES</string><string>España</string><string>Barcelona, España</string><gate.util.SimpleFeatureMapImpl serialization="custom"><gate.util.SimpleMapImpl><default><capacity>3</capacity><count>2</count><theKeys><string>coordinates</string><string>type</string><null/></theKeys><theValues><list><list><list><double>2.052477</double><double>41.317048</double></list><list><double>2.052477</double><double>41.468266</double></list><list><double>2.229978</double><double>41.468266</double></list><list><double>2.229978</double><double>41.317048</double></list></list></list><string>Polygon</string><null/></theValues></default></gate.util.SimpleMapImpl></gate.util.SimpleFeatureMapImpl><string>city</string><string>Barcelona</string><gate.util.SimpleFeatureMapImpl serialization="custom"><gate.util.SimpleMapImpl><default><capacity>3</capacity><count>0</count><theKeys><null/><null/><null/></theKeys><theValues><null/><null/><null/></theValues></default></gate.util.SimpleMapImpl></gate.util.SimpleFeatureMapImpl><string>1a27537478dd8e38</string><string>https://api.twitter.com/1.1/geo/id/1a27537478dd8e38.json</string><null/><null/><null/></theValues></default></gate.util.SimpleMapImpl></value></gate.corpora.ObjectWrapper>]]></Value>
</Feature>
<Feature>
  <Name className="java.lang.String">lang</Name>
  <Value className="java.lang.String">und</Value>
</Feature>
<Feature>
  <Name className="java.lang.String">quote_count</Name>
  <Value className="java.lang.Long">0</Value>
</Feature>
<Feature>
  <Name className="java.lang.String">favorited</Name>
  <Value className="java.lang.Boolean">false</Value>
</Feature>
<Feature>
  <Name className="java.lang.String">possibly_sensitive</Name>
  <Value className="java.lang.Boolean">false</Value>
</Feature>
<Feature>
  <Name className="java.lang.String">truncated</Name>
  <Value className="java.lang.Boolean">false</Value>
</Feature>
<Feature>
  <Name className="java.lang.String">timestamp_ms</Name>
  <Value className="java.lang.String">1512042035525</Value>
</Feature>
<Feature>
  <Name className="java.lang.String">reply_count</Name>
  <Value className="java.lang.Long">0</Value>
</Feature>
<Feature>
  <Name className="java.lang.String">display_text_range</Name>
  <Value className="gate.corpora.ObjectWrapper"><![CDATA[<?xml version='1.1'?><gate.corpora.ObjectWrapper><value class="list"><long>0</long><long>5</long></value></gate.corpora.ObjectWrapper>]]></Value>
</Feature>
<Feature>
  <Name className="java.lang.String">quoted_status_id_str</Name>
  <Value className="java.lang.String">932118541817360384</Value>
</Feature>
<Feature>
  <Name className="java.lang.String">user</Name>
  <Value className="gate.corpora.ObjectWrapper"><![CDATA[<?xml version='1.1'?><gate.corpora.ObjectWrapper><value class="gate.util.SimpleFeatureMapImpl" serialization="custom"><gate.util.SimpleMapImpl><default><capacity>48</capacity><count>39</count><theKeys><string>utc_offset</string><string>friends_count</string><string>profile_image_url_https</string><string>listed_count</string><string>profile_background_image_url</string><string>default_profile_image</string><string>favourites_count</string><string>description</string><string>created_at</string><string>is_translator</string><string>profile_background_image_url_https</string><string>protected</string><string>screen_name</string><string>id_str</string><string>profile_link_color</string><string>translator_type</string><string>id</string><string>geo_enabled</string><string>profile_background_color</string><string>lang</string><string>profile_sidebar_border_color</string><string>profile_text_color</string><string>verified</string><string>profile_image_url</string><string>time_zone</string><string>url</string><string>contributors_enabled</string><string>profile_background_tile</string><string>profile_banner_url</string><string>statuses_count</string><string>follow_request_sent</string><string>followers_count</string><string>profile_use_background_image</string><string>default_profile</string><string>following</string><string>name</string><string>location</string><string>profile_sidebar_fill_color</string><string>notifications</string><null/><null/><null/><null/><null/><null/><null/><null/><null/></theKeys><theValues><long>3600</long><long>292</long><string>https://pbs.twimg.com/profile_images/926451428083879937/WotlKxEv_normal.jpg</string><long>5</long><string>http://pbs.twimg.com/profile_background_images/692422655362908160/sG4ULj6D.jpg</string><boolean>false</boolean><long>5018</long><string>Mare de Déu del brioix de mantega...</string><string>Sun Jul 05 18:57:13 +0000 2009</string><boolean>false</boolean><string>https://pbs.twimg.com/profile_background_images/692422655362908160/sG4ULj6D.jpg</string><boolean>false</boolean><string>Llesquins</string><string>53976096</string><string>F5ABB5</string><string>none</string><long>53976096</long><boolean>true</boolean><string>F5ABB5</string><string>es</string><string>000000</string><string>000000</string><boolean>false</boolean><string>http://pbs.twimg.com/profile_images/926451428083879937/WotlKxEv_normal.jpg</string><string>Madrid</string><string>http://samusa.tumblr.com</string><boolean>false</boolean><boolean>true</boolean><string>https://pbs.twimg.com/profile_banners/53976096/1506637573</string><long>71431</long><null/><long>131</long><boolean>true</boolean><boolean>false</boolean><null/><string>Ari 🎗️</string><string>Can Pixa, República Catalana</string><string>000000</string><null/><null/><null/><null/><null/><null/><null/><null/><null/><null/></theValues></default></gate.util.SimpleMapImpl></value></gate.corpora.ObjectWrapper>]]></Value>
</Feature>
</Annotation>
<Annotation Id="1" Type="urls" StartNode="6" EndNode="29">
<Feature>
  <Name className="java.lang.String">expanded_url</Name>
  <Value className="java.lang.String">https://twitter.com/SoyChuchoTec/status/932118541817360384</Value>
</Feature>
<Feature>
  <Name className="java.lang.String">display_url</Name>
  <Value className="java.lang.String">twitter.com/SoyChuchoTec/s…</Value>
</Feature>
<Feature>
  <Name className="java.lang.String">url</Name>
  <Value className="java.lang.String">https://t.co/O6qt1o6hbW</Value>
</Feature>
</Annotation>
</AnnotationSet>

</GateDocument>
