<?xml version='1.0' encoding='UTF-8'?>
<GateDocument version="3">
<!-- The document's features-->

<GateDocumentFeatures>
<Feature>
  <Name className="java.lang.String">gate.SourceURL</Name>
  <Value className="java.lang.String">file:/C:/Users/filip/AIW2017_P3_G3/data/json/936203820434116608.json</Value>
</Feature>
<Feature>
  <Name className="java.lang.String">MimeType</Name>
  <Value className="java.lang.String">text/x-json-twitter</Value>
</Feature>
<Feature>
  <Name className="java.lang.String">docNewLineType</Name>
  <Value className="java.lang.String"></Value>
</Feature>
</GateDocumentFeatures>
<!-- The document content area with serialized nodes -->

<TextWithNodes><Node id="0"/>Aquest<Node id="6"/> <Node id="7"/>es<Node id="9"/> <Node id="10"/>el<Node id="12"/> <Node id="13"/>director<Node id="21"/> <Node id="22"/>adjunt<Node id="28"/> <Node id="29"/>de<Node id="31"/> <Node id="32"/>l<Node id="33"/>'<Node id="34"/>@<Node id="35"/>sport<Node id="40"/>,<Node id="41"/> <Node id="42"/>que<Node id="45"/> <Node id="46"/>parla<Node id="51"/> <Node id="52"/>de<Node id="54"/> <Node id="55"/>feixisme<Node id="63"/> <Node id="64"/>a<Node id="65"/> <Node id="66"/>la<Node id="68"/> <Node id="69"/>vegada<Node id="75"/> <Node id="76"/>que<Node id="79"/> <Node id="80"/>recolza<Node id="87"/> <Node id="88"/>que<Node id="91"/> <Node id="92"/>fotin<Node id="97"/> <Node id="98"/>fora<Node id="102"/> <Node id="103"/>a<Node id="104"/> <Node id="105"/>35<Node id="107"/> <Node id="108"/>persone<Node id="115"/>…<Node id="116"/> <Node id="117"/>https://t.<Node id="127"/>co<Node id="129"/>/Cmttd1kJx0<Node id="140"/>
<Node id="141"/>
<Node id="142"/></TextWithNodes>
<!-- The default annotation set -->

<AnnotationSet>
<Annotation Id="0" Type="Tweet" StartNode="0" EndNode="140">
<Feature>
  <Name className="java.lang.String">extended_tweet</Name>
  <Value className="gate.corpora.ObjectWrapper"><![CDATA[<?xml version='1.1'?><gate.corpora.ObjectWrapper><value class="gate.util.SimpleFeatureMapImpl" serialization="custom"><gate.util.SimpleMapImpl><default><capacity>3</capacity><count>3</count><theKeys><string>entities</string><string>full_text</string><string>display_text_range</string></theKeys><theValues><gate.util.SimpleFeatureMapImpl serialization="custom"><gate.util.SimpleMapImpl><default><capacity>6</capacity><count>4</count><theKeys><string>urls</string><string>hashtags</string><string>user_mentions</string><string>symbols</string><null/><null/></theKeys><theValues><list><gate.util.SimpleFeatureMapImpl serialization="custom"><gate.util.SimpleMapImpl><default><capacity>6</capacity><count>4</count><theKeys><string>display_url</string><string>indices</string><string>expanded_url</string><string>url</string><null/><null/></theKeys><theValues><string>twitter.com/LluisMascaro/s…</string><list><long>127</long><long>150</long></list><string>https://twitter.com/LluisMascaro/status/926371590694195201</string><string>https://t.co/dJd0JGCIbq</string><null/><null/></theValues></default></gate.util.SimpleMapImpl></gate.util.SimpleFeatureMapImpl></list><list/><list><gate.util.SimpleFeatureMapImpl serialization="custom"><gate.util.SimpleMapImpl><default><capacity>6</capacity><count>5</count><theKeys><string>indices</string><string>screen_name</string><string>id_str</string><string>name</string><string>id</string><null/></theKeys><theValues><list><long>34</long><long>40</long></list><string>sport</string><string>19343904</string><string>Diario SPORT</string><long>19343904</long><null/></theValues></default></gate.util.SimpleMapImpl></gate.util.SimpleFeatureMapImpl></list><list/><null/><null/></theValues></default></gate.util.SimpleMapImpl></gate.util.SimpleFeatureMapImpl><string>Aquest es el director adjunt de l'@sport, que parla de feixisme a la vegada que recolza que fotin fora a 35 persones del diari https://t.co/dJd0JGCIbq</string><list><long>0</long><long>126</long></list></theValues></default></gate.util.SimpleMapImpl></value></gate.corpora.ObjectWrapper>]]></Value>
</Feature>
<Feature>
  <Name className="java.lang.String">quoted_status</Name>
  <Value className="gate.corpora.ObjectWrapper"><![CDATA[<?xml version='1.1'?><gate.corpora.ObjectWrapper><value class="gate.util.SimpleFeatureMapImpl" serialization="custom"><gate.util.SimpleMapImpl><default><capacity>48</capacity><count>31</count><theKeys><string>extended_tweet</string><string>in_reply_to_status_id_str</string><string>in_reply_to_status_id</string><string>created_at</string><string>in_reply_to_user_id_str</string><string>source</string><string>quoted_status_id</string><string>retweet_count</string><string>retweeted</string><string>geo</string><string>filter_level</string><string>in_reply_to_screen_name</string><string>is_quote_status</string><string>id_str</string><string>in_reply_to_user_id</string><string>favorite_count</string><string>id</string><string>text</string><string>place</string><string>lang</string><string>quote_count</string><string>favorited</string><string>possibly_sensitive</string><string>coordinates</string><string>truncated</string><string>reply_count</string><string>entities</string><string>display_text_range</string><string>quoted_status_id_str</string><string>contributors</string><string>user</string><null/><null/><null/><null/><null/><null/><null/><null/><null/><null/><null/><null/><null/><null/><null/><null/><null/></theKeys><theValues><gate.util.SimpleFeatureMapImpl serialization="custom"><gate.util.SimpleMapImpl><default><capacity>3</capacity><count>3</count><theKeys><string>entities</string><string>full_text</string><string>display_text_range</string></theKeys><theValues><gate.util.SimpleFeatureMapImpl serialization="custom"><gate.util.SimpleMapImpl><default><capacity>6</capacity><count>4</count><theKeys><string>urls</string><string>hashtags</string><string>user_mentions</string><string>symbols</string><null/><null/></theKeys><theValues><list><gate.util.SimpleFeatureMapImpl serialization="custom"><gate.util.SimpleMapImpl><default><capacity>6</capacity><count>4</count><theKeys><string>display_url</string><string>indices</string><string>expanded_url</string><string>url</string><null/><null/></theKeys><theValues><string>twitter.com/RamonAndreuCau…</string><list><long>141</long><long>164</long></list><string>https://twitter.com/RamonAndreuCauf/status/926362538610225152</string><string>https://t.co/HfTnDwHh6S</string><null/><null/></theValues></default></gate.util.SimpleMapImpl></gate.util.SimpleFeatureMapImpl></list><list/><list/><list/><null/><null/></theValues></default></gate.util.SimpleMapImpl></gate.util.SimpleFeatureMapImpl><string>S'ha de lluitar de totes les maneres possibles contra el feixisme. No es pot fer veure que no passa res. Perque sí passa. I molt. Llibertat! https://t.co/HfTnDwHh6S</string><list><long>0</long><long>140</long></list></theValues></default></gate.util.SimpleMapImpl></gate.util.SimpleFeatureMapImpl><null/><null/><string>Fri Nov 03 08:52:53 +0000 2017</string><null/><string>&lt;a href="https://about.twitter.com/products/tweetdeck" rel="nofollow">TweetDeck&lt;/a></string><long>926362538610225152</long><long>4</long><boolean>false</boolean><null/><string>low</string><null/><boolean>true</boolean><string>926371590694195201</string><null/><long>15</long><long>926371590694195201</long><string>S'ha de lluitar de totes les maneres possibles contra el feixisme. No es pot fer veure que no passa res. Perque sí… https://t.co/NNNrjKFaQP</string><null/><string>und</string><long>1</long><boolean>false</boolean><boolean>false</boolean><null/><boolean>true</boolean><long>26</long><gate.util.SimpleFeatureMapImpl serialization="custom"><gate.util.SimpleMapImpl><default><capacity>6</capacity><count>4</count><theKeys><string>urls</string><string>hashtags</string><string>user_mentions</string><string>symbols</string><null/><null/></theKeys><theValues><list><gate.util.SimpleFeatureMapImpl serialization="custom"><gate.util.SimpleMapImpl><default><capacity>6</capacity><count>4</count><theKeys><string>display_url</string><string>indices</string><string>expanded_url</string><string>url</string><null/><null/></theKeys><theValues><string>twitter.com/i/web/status/9…</string><list><long>116</long><long>139</long></list><string>https://twitter.com/i/web/status/926371590694195201</string><string>https://t.co/NNNrjKFaQP</string><null/><null/></theValues></default></gate.util.SimpleMapImpl></gate.util.SimpleFeatureMapImpl></list><list/><list/><list/><null/><null/></theValues></default></gate.util.SimpleMapImpl></gate.util.SimpleFeatureMapImpl><list><long>0</long><long>140</long></list><string>926362538610225152</string><null/><gate.util.SimpleFeatureMapImpl serialization="custom"><gate.util.SimpleMapImpl><default><capacity>48</capacity><count>39</count><theKeys><string>utc_offset</string><string>friends_count</string><string>profile_image_url_https</string><string>listed_count</string><string>profile_background_image_url</string><string>default_profile_image</string><string>favourites_count</string><string>description</string><string>created_at</string><string>is_translator</string><string>profile_background_image_url_https</string><string>protected</string><string>screen_name</string><string>id_str</string><string>profile_link_color</string><string>translator_type</string><string>id</string><string>geo_enabled</string><string>profile_background_color</string><string>lang</string><string>profile_sidebar_border_color</string><string>profile_text_color</string><string>verified</string><string>profile_image_url</string><string>time_zone</string><string>url</string><string>contributors_enabled</string><string>profile_background_tile</string><string>profile_banner_url</string><string>statuses_count</string><string>follow_request_sent</string><string>followers_count</string><string>profile_use_background_image</string><string>default_profile</string><string>following</string><string>name</string><string>location</string><string>profile_sidebar_fill_color</string><string>notifications</string><null/><null/><null/><null/><null/><null/><null/><null/><null/></theKeys><theValues><long>-28800</long><long>729</long><string>https://pbs.twimg.com/profile_images/839943685362044929/9S3_PvGg_normal.jpg</string><long>732</long><string>http://abs.twimg.com/images/themes/theme1/bg.png</string><boolean>false</boolean><long>43</long><string>Periodista 👨🏻‍💻Marido de Lluïsa 👸Nadador 🏊🏽</string><string>Wed Jan 20 20:02:25 +0000 2010</string><boolean>false</boolean><string>https://abs.twimg.com/images/themes/theme1/bg.png</string><boolean>false</boolean><string>LluisMascaro</string><string>106818870</string><string>1DA1F2</string><string>none</string><long>106818870</long><boolean>false</boolean><string>C0DEED</string><string>es</string><string>C0DEED</string><string>333333</string><boolean>false</boolean><string>http://pbs.twimg.com/profile_images/839943685362044929/9S3_PvGg_normal.jpg</string><string>Pacific Time (US &amp; Canada)</string><string>http://sport.es</string><boolean>false</boolean><boolean>false</boolean><string>https://pbs.twimg.com/profile_banners/106818870/1487681348</string><long>5702</long><null/><long>57040</long><boolean>true</boolean><boolean>true</boolean><null/><string>Lluís Mascaró</string><string>Barcelona</string><string>DDEEF6</string><null/><null/><null/><null/><null/><null/><null/><null/><null/><null/></theValues></default></gate.util.SimpleMapImpl></gate.util.SimpleFeatureMapImpl><null/><null/><null/><null/><null/><null/><null/><null/><null/><null/><null/><null/><null/><null/><null/><null/><null/></theValues></default></gate.util.SimpleMapImpl></value></gate.corpora.ObjectWrapper>]]></Value>
</Feature>
<Feature>
  <Name className="java.lang.String">created_at</Name>
  <Value className="java.lang.String">Thu Nov 30 12:02:39 +0000 2017</Value>
</Feature>
<Feature>
  <Name className="java.lang.String">source</Name>
  <Value className="java.lang.String">&lt;a href="http://twitter.com/download/android" rel="nofollow">Twitter for Android&lt;/a></Value>
</Feature>
<Feature>
  <Name className="java.lang.String">quoted_status_id</Name>
  <Value className="java.lang.Long">926371590694195201</Value>
</Feature>
<Feature>
  <Name className="java.lang.String">retweet_count</Name>
  <Value className="java.lang.Long">0</Value>
</Feature>
<Feature>
  <Name className="java.lang.String">retweeted</Name>
  <Value className="java.lang.Boolean">false</Value>
</Feature>
<Feature>
  <Name className="java.lang.String">filter_level</Name>
  <Value className="java.lang.String">low</Value>
</Feature>
<Feature>
  <Name className="java.lang.String">is_quote_status</Name>
  <Value className="java.lang.Boolean">true</Value>
</Feature>
<Feature>
  <Name className="java.lang.String">id_str</Name>
  <Value className="java.lang.String">936203820434116608</Value>
</Feature>
<Feature>
  <Name className="java.lang.String">favorite_count</Name>
  <Value className="java.lang.Long">0</Value>
</Feature>
<Feature>
  <Name className="java.lang.String">id</Name>
  <Value className="java.lang.Long">936203820434116608</Value>
</Feature>
<Feature>
  <Name className="java.lang.String">place</Name>
  <Value className="gate.corpora.ObjectWrapper"><![CDATA[<?xml version='1.1'?><gate.corpora.ObjectWrapper><value class="gate.util.SimpleFeatureMapImpl" serialization="custom"><gate.util.SimpleMapImpl><default><capacity>12</capacity><count>9</count><theKeys><string>country_code</string><string>country</string><string>full_name</string><string>bounding_box</string><string>place_type</string><string>name</string><string>attributes</string><string>id</string><string>url</string><null/><null/><null/></theKeys><theValues><string>ES</string><string>España</string><string>Barcelona, España</string><gate.util.SimpleFeatureMapImpl serialization="custom"><gate.util.SimpleMapImpl><default><capacity>3</capacity><count>2</count><theKeys><string>coordinates</string><string>type</string><null/></theKeys><theValues><list><list><list><double>2.052477</double><double>41.317048</double></list><list><double>2.052477</double><double>41.468266</double></list><list><double>2.229978</double><double>41.468266</double></list><list><double>2.229978</double><double>41.317048</double></list></list></list><string>Polygon</string><null/></theValues></default></gate.util.SimpleMapImpl></gate.util.SimpleFeatureMapImpl><string>city</string><string>Barcelona</string><gate.util.SimpleFeatureMapImpl serialization="custom"><gate.util.SimpleMapImpl><default><capacity>3</capacity><count>0</count><theKeys><null/><null/><null/></theKeys><theValues><null/><null/><null/></theValues></default></gate.util.SimpleMapImpl></gate.util.SimpleFeatureMapImpl><string>1a27537478dd8e38</string><string>https://api.twitter.com/1.1/geo/id/1a27537478dd8e38.json</string><null/><null/><null/></theValues></default></gate.util.SimpleMapImpl></value></gate.corpora.ObjectWrapper>]]></Value>
</Feature>
<Feature>
  <Name className="java.lang.String">lang</Name>
  <Value className="java.lang.String">spanish</Value>
</Feature>
<Feature>
  <Name className="java.lang.String">quote_count</Name>
  <Value className="java.lang.Long">0</Value>
</Feature>
<Feature>
  <Name className="java.lang.String">favorited</Name>
  <Value className="java.lang.Boolean">false</Value>
</Feature>
<Feature>
  <Name className="java.lang.String">possibly_sensitive</Name>
  <Value className="java.lang.Boolean">false</Value>
</Feature>
<Feature>
  <Name className="java.lang.String">truncated</Name>
  <Value className="java.lang.Boolean">true</Value>
</Feature>
<Feature>
  <Name className="java.lang.String">timestamp_ms</Name>
  <Value className="java.lang.String">1512043359274</Value>
</Feature>
<Feature>
  <Name className="java.lang.String">reply_count</Name>
  <Value className="java.lang.Long">0</Value>
</Feature>
<Feature>
  <Name className="java.lang.String">display_text_range</Name>
  <Value className="gate.corpora.ObjectWrapper"><![CDATA[<?xml version='1.1'?><gate.corpora.ObjectWrapper><value class="list"><long>0</long><long>140</long></value></gate.corpora.ObjectWrapper>]]></Value>
</Feature>
<Feature>
  <Name className="java.lang.String">quoted_status_id_str</Name>
  <Value className="java.lang.String">926371590694195201</Value>
</Feature>
<Feature>
  <Name className="java.lang.String">user</Name>
  <Value className="gate.corpora.ObjectWrapper"><![CDATA[<?xml version='1.1'?><gate.corpora.ObjectWrapper><value class="gate.util.SimpleFeatureMapImpl" serialization="custom"><gate.util.SimpleMapImpl><default><capacity>48</capacity><count>39</count><theKeys><string>utc_offset</string><string>friends_count</string><string>profile_image_url_https</string><string>listed_count</string><string>profile_background_image_url</string><string>default_profile_image</string><string>favourites_count</string><string>description</string><string>created_at</string><string>is_translator</string><string>profile_background_image_url_https</string><string>protected</string><string>screen_name</string><string>id_str</string><string>profile_link_color</string><string>translator_type</string><string>id</string><string>geo_enabled</string><string>profile_background_color</string><string>lang</string><string>profile_sidebar_border_color</string><string>profile_text_color</string><string>verified</string><string>profile_image_url</string><string>time_zone</string><string>url</string><string>contributors_enabled</string><string>profile_background_tile</string><string>profile_banner_url</string><string>statuses_count</string><string>follow_request_sent</string><string>followers_count</string><string>profile_use_background_image</string><string>default_profile</string><string>following</string><string>name</string><string>location</string><string>profile_sidebar_fill_color</string><string>notifications</string><null/><null/><null/><null/><null/><null/><null/><null/><null/></theKeys><theValues><long>3600</long><long>1194</long><string>https://pbs.twimg.com/profile_images/2621085898/s3x6i6ji4znhgxslx50e_normal.jpeg</string><long>189</long><string>http://pbs.twimg.com/profile_background_images/661309140/tpwaqdsvy3ok6n5ylxj5.jpeg</string><boolean>false</boolean><long>155</long><string>Periodista. Quan es pot</string><string>Thu Sep 23 17:06:13 +0000 2010</string><boolean>false</boolean><string>https://pbs.twimg.com/profile_background_images/661309140/tpwaqdsvy3ok6n5ylxj5.jpeg</string><boolean>false</boolean><string>Elwood_White</string><string>194191462</string><string>0084B4</string><string>none</string><long>194191462</long><boolean>true</boolean><string>022330</string><string>es</string><string>A8C7F7</string><string>333333</string><boolean>false</boolean><string>http://pbs.twimg.com/profile_images/2621085898/s3x6i6ji4znhgxslx50e_normal.jpeg</string><string>Madrid</string><string>http://sport.es</string><boolean>false</boolean><boolean>false</boolean><string>https://pbs.twimg.com/profile_banners/194191462/1477435227</string><long>40119</long><null/><long>4936</long><boolean>true</boolean><boolean>false</boolean><null/><string>Jordi Blanco Duch</string><string>Barcelona city</string><string>C0DFEC</string><null/><null/><null/><null/><null/><null/><null/><null/><null/><null/></theValues></default></gate.util.SimpleMapImpl></value></gate.corpora.ObjectWrapper>]]></Value>
</Feature>
</Annotation>
<Annotation Id="256" Type="SpaceToken" StartNode="140" EndNode="141">
<Feature>
  <Name className="java.lang.String">string</Name>
  <Value className="java.lang.String">
</Value>
</Feature>
<Feature>
  <Name className="java.lang.String">length</Name>
  <Value className="java.lang.String">1</Value>
</Feature>
<Feature>
  <Name className="java.lang.String">kind</Name>
  <Value className="java.lang.String">control</Value>
</Feature>
</Annotation>
<Annotation Id="257" Type="SpaceToken" StartNode="141" EndNode="142">
<Feature>
  <Name className="java.lang.String">string</Name>
  <Value className="java.lang.String">
</Value>
</Feature>
<Feature>
  <Name className="java.lang.String">length</Name>
  <Value className="java.lang.String">1</Value>
</Feature>
<Feature>
  <Name className="java.lang.String">kind</Name>
  <Value className="java.lang.String">control</Value>
</Feature>
</Annotation>
<Annotation Id="354" Type="Lookup" StartNode="7" EndNode="9">
<Feature>
  <Name className="java.lang.String">majorType</Name>
  <Value className="java.lang.String">country_code</Value>
</Feature>
</Annotation>
<Annotation Id="355" Type="Lookup" StartNode="13" EndNode="21">
<Feature>
  <Name className="java.lang.String">majorType</Name>
  <Value className="java.lang.String">jobtitle</Value>
</Feature>
</Annotation>
<Annotation Id="356" Type="Lookup" StartNode="29" EndNode="31">
<Feature>
  <Name className="java.lang.String">majorType</Name>
  <Value className="java.lang.String">country_code</Value>
</Feature>
</Annotation>
<Annotation Id="357" Type="Lookup" StartNode="29" EndNode="31">
<Feature>
  <Name className="java.lang.String">majorType</Name>
  <Value className="java.lang.String">surname</Value>
</Feature>
<Feature>
  <Name className="java.lang.String">minorType</Name>
  <Value className="java.lang.String">prefix</Value>
</Feature>
</Annotation>
<Annotation Id="358" Type="Lookup" StartNode="52" EndNode="54">
<Feature>
  <Name className="java.lang.String">majorType</Name>
  <Value className="java.lang.String">country_code</Value>
</Feature>
</Annotation>
<Annotation Id="359" Type="Lookup" StartNode="52" EndNode="54">
<Feature>
  <Name className="java.lang.String">majorType</Name>
  <Value className="java.lang.String">surname</Value>
</Feature>
<Feature>
  <Name className="java.lang.String">minorType</Name>
  <Value className="java.lang.String">prefix</Value>
</Feature>
</Annotation>
<Annotation Id="360" Type="Lookup" StartNode="66" EndNode="68">
<Feature>
  <Name className="java.lang.String">majorType</Name>
  <Value className="java.lang.String">country_code</Value>
</Feature>
</Annotation>
<Annotation Id="361" Type="Lookup" StartNode="127" EndNode="129">
<Feature>
  <Name className="java.lang.String">majorType</Name>
  <Value className="java.lang.String">country_code</Value>
</Feature>
</Annotation>
<Annotation Id="362" Type="Lookup" StartNode="127" EndNode="129">
<Feature>
  <Name className="java.lang.String">majorType</Name>
  <Value className="java.lang.String">url_key</Value>
</Feature>
</Annotation>
<Annotation Id="363" Type="Split" StartNode="140" EndNode="142">
<Feature>
  <Name className="java.lang.String">kind</Name>
  <Value className="java.lang.String">external</Value>
</Feature>
</Annotation>
<Annotation Id="364" Type="Sentence" StartNode="0" EndNode="140">
</Annotation>
<Annotation Id="365" Type="Upper" StartNode="0" EndNode="6">
<Feature>
  <Name className="java.lang.String">rule</Name>
  <Value className="java.lang.String">Upper</Value>
</Feature>
</Annotation>
<Annotation Id="366" Type="Upper" StartNode="10" EndNode="12">
<Feature>
  <Name className="java.lang.String">rule</Name>
  <Value className="java.lang.String">Upper</Value>
</Feature>
</Annotation>
<Annotation Id="367" Type="ClosedClass" StartNode="29" EndNode="31">
<Feature>
  <Name className="java.lang.String">rule</Name>
  <Value className="java.lang.String">ClosedClass</Value>
</Feature>
</Annotation>
<Annotation Id="368" Type="ClosedClass" StartNode="32" EndNode="33">
<Feature>
  <Name className="java.lang.String">rule</Name>
  <Value className="java.lang.String">ClosedClass</Value>
</Feature>
</Annotation>
<Annotation Id="369" Type="ClosedClass" StartNode="103" EndNode="104">
<Feature>
  <Name className="java.lang.String">rule</Name>
  <Value className="java.lang.String">ClosedClass</Value>
</Feature>
</Annotation>
<Annotation Id="370" Type="JobTitle" StartNode="13" EndNode="21">
<Feature>
  <Name className="java.lang.String">rule</Name>
  <Value className="java.lang.String">JobTitle1</Value>
</Feature>
</Annotation>
<Annotation Id="371" Type="Unknown" StartNode="0" EndNode="6">
<Feature>
  <Name className="java.lang.String">rule</Name>
  <Value className="java.lang.String">Unknown</Value>
</Feature>
<Feature>
  <Name className="java.lang.String">kind</Name>
  <Value className="java.lang.String">PN</Value>
</Feature>
</Annotation>
<Annotation Id="372" Type="Unknown" StartNode="10" EndNode="12">
<Feature>
  <Name className="java.lang.String">rule</Name>
  <Value className="java.lang.String">Unknown</Value>
</Feature>
<Feature>
  <Name className="java.lang.String">kind</Name>
  <Value className="java.lang.String">PN</Value>
</Feature>
</Annotation>
<Annotation Id="188" Type="Token" StartNode="0" EndNode="6">
<Feature>
  <Name className="java.lang.String">length</Name>
  <Value className="java.lang.String">6</Value>
</Feature>
<Feature>
  <Name className="java.lang.String">orth</Name>
  <Value className="java.lang.String">upperInitial</Value>
</Feature>
<Feature>
  <Name className="java.lang.String">string</Name>
  <Value className="java.lang.String">Aquest</Value>
</Feature>
<Feature>
  <Name className="java.lang.String">category</Name>
  <Value className="java.lang.String">NNP</Value>
</Feature>
<Feature>
  <Name className="java.lang.String">kind</Name>
  <Value className="java.lang.String">word</Value>
</Feature>
</Annotation>
<Annotation Id="189" Type="SpaceToken" StartNode="6" EndNode="7">
<Feature>
  <Name className="java.lang.String">string</Name>
  <Value className="java.lang.String"> </Value>
</Feature>
<Feature>
  <Name className="java.lang.String">length</Name>
  <Value className="java.lang.String">1</Value>
</Feature>
<Feature>
  <Name className="java.lang.String">kind</Name>
  <Value className="java.lang.String">space</Value>
</Feature>
</Annotation>
<Annotation Id="190" Type="Token" StartNode="7" EndNode="9">
<Feature>
  <Name className="java.lang.String">length</Name>
  <Value className="java.lang.String">2</Value>
</Feature>
<Feature>
  <Name className="java.lang.String">orth</Name>
  <Value className="java.lang.String">lowercase</Value>
</Feature>
<Feature>
  <Name className="java.lang.String">origString</Name>
  <Value className="java.lang.String">es</Value>
</Feature>
<Feature>
  <Name className="java.lang.String">string</Name>
  <Value className="java.lang.String">he's</Value>
</Feature>
<Feature>
  <Name className="java.lang.String">category</Name>
  <Value className="java.lang.String">VBZ</Value>
</Feature>
<Feature>
  <Name className="java.lang.String">kind</Name>
  <Value className="java.lang.String">word</Value>
</Feature>
</Annotation>
<Annotation Id="191" Type="SpaceToken" StartNode="9" EndNode="10">
<Feature>
  <Name className="java.lang.String">string</Name>
  <Value className="java.lang.String"> </Value>
</Feature>
<Feature>
  <Name className="java.lang.String">length</Name>
  <Value className="java.lang.String">1</Value>
</Feature>
<Feature>
  <Name className="java.lang.String">kind</Name>
  <Value className="java.lang.String">space</Value>
</Feature>
</Annotation>
<Annotation Id="192" Type="Token" StartNode="10" EndNode="12">
<Feature>
  <Name className="java.lang.String">length</Name>
  <Value className="java.lang.String">2</Value>
</Feature>
<Feature>
  <Name className="java.lang.String">orth</Name>
  <Value className="java.lang.String">lowercase</Value>
</Feature>
<Feature>
  <Name className="java.lang.String">string</Name>
  <Value className="java.lang.String">el</Value>
</Feature>
<Feature>
  <Name className="java.lang.String">category</Name>
  <Value className="java.lang.String">NNP</Value>
</Feature>
<Feature>
  <Name className="java.lang.String">kind</Name>
  <Value className="java.lang.String">word</Value>
</Feature>
</Annotation>
<Annotation Id="193" Type="SpaceToken" StartNode="12" EndNode="13">
<Feature>
  <Name className="java.lang.String">string</Name>
  <Value className="java.lang.String"> </Value>
</Feature>
<Feature>
  <Name className="java.lang.String">length</Name>
  <Value className="java.lang.String">1</Value>
</Feature>
<Feature>
  <Name className="java.lang.String">kind</Name>
  <Value className="java.lang.String">space</Value>
</Feature>
</Annotation>
<Annotation Id="194" Type="Token" StartNode="13" EndNode="21">
<Feature>
  <Name className="java.lang.String">length</Name>
  <Value className="java.lang.String">8</Value>
</Feature>
<Feature>
  <Name className="java.lang.String">orth</Name>
  <Value className="java.lang.String">lowercase</Value>
</Feature>
<Feature>
  <Name className="java.lang.String">string</Name>
  <Value className="java.lang.String">director</Value>
</Feature>
<Feature>
  <Name className="java.lang.String">category</Name>
  <Value className="java.lang.String">NN</Value>
</Feature>
<Feature>
  <Name className="java.lang.String">kind</Name>
  <Value className="java.lang.String">word</Value>
</Feature>
</Annotation>
<Annotation Id="195" Type="SpaceToken" StartNode="21" EndNode="22">
<Feature>
  <Name className="java.lang.String">string</Name>
  <Value className="java.lang.String"> </Value>
</Feature>
<Feature>
  <Name className="java.lang.String">length</Name>
  <Value className="java.lang.String">1</Value>
</Feature>
<Feature>
  <Name className="java.lang.String">kind</Name>
  <Value className="java.lang.String">space</Value>
</Feature>
</Annotation>
<Annotation Id="196" Type="Token" StartNode="22" EndNode="28">
<Feature>
  <Name className="java.lang.String">length</Name>
  <Value className="java.lang.String">6</Value>
</Feature>
<Feature>
  <Name className="java.lang.String">orth</Name>
  <Value className="java.lang.String">lowercase</Value>
</Feature>
<Feature>
  <Name className="java.lang.String">origString</Name>
  <Value className="java.lang.String">adjunt</Value>
</Feature>
<Feature>
  <Name className="java.lang.String">string</Name>
  <Value className="java.lang.String">adjust</Value>
</Feature>
<Feature>
  <Name className="java.lang.String">category</Name>
  <Value className="java.lang.String">VBP</Value>
</Feature>
<Feature>
  <Name className="java.lang.String">kind</Name>
  <Value className="java.lang.String">word</Value>
</Feature>
</Annotation>
<Annotation Id="197" Type="SpaceToken" StartNode="28" EndNode="29">
<Feature>
  <Name className="java.lang.String">string</Name>
  <Value className="java.lang.String"> </Value>
</Feature>
<Feature>
  <Name className="java.lang.String">length</Name>
  <Value className="java.lang.String">1</Value>
</Feature>
<Feature>
  <Name className="java.lang.String">kind</Name>
  <Value className="java.lang.String">space</Value>
</Feature>
</Annotation>
<Annotation Id="198" Type="Token" StartNode="29" EndNode="31">
<Feature>
  <Name className="java.lang.String">length</Name>
  <Value className="java.lang.String">2</Value>
</Feature>
<Feature>
  <Name className="java.lang.String">orth</Name>
  <Value className="java.lang.String">lowercase</Value>
</Feature>
<Feature>
  <Name className="java.lang.String">string</Name>
  <Value className="java.lang.String">de</Value>
</Feature>
<Feature>
  <Name className="java.lang.String">category</Name>
  <Value className="java.lang.String">IN</Value>
</Feature>
<Feature>
  <Name className="java.lang.String">kind</Name>
  <Value className="java.lang.String">word</Value>
</Feature>
</Annotation>
<Annotation Id="199" Type="SpaceToken" StartNode="31" EndNode="32">
<Feature>
  <Name className="java.lang.String">string</Name>
  <Value className="java.lang.String"> </Value>
</Feature>
<Feature>
  <Name className="java.lang.String">length</Name>
  <Value className="java.lang.String">1</Value>
</Feature>
<Feature>
  <Name className="java.lang.String">kind</Name>
  <Value className="java.lang.String">space</Value>
</Feature>
</Annotation>
<Annotation Id="200" Type="Token" StartNode="32" EndNode="33">
<Feature>
  <Name className="java.lang.String">length</Name>
  <Value className="java.lang.String">1</Value>
</Feature>
<Feature>
  <Name className="java.lang.String">orth</Name>
  <Value className="java.lang.String">lowercase</Value>
</Feature>
<Feature>
  <Name className="java.lang.String">string</Name>
  <Value className="java.lang.String">l</Value>
</Feature>
<Feature>
  <Name className="java.lang.String">category</Name>
  <Value className="java.lang.String">PRP</Value>
</Feature>
<Feature>
  <Name className="java.lang.String">kind</Name>
  <Value className="java.lang.String">word</Value>
</Feature>
</Annotation>
<Annotation Id="201" Type="Token" StartNode="33" EndNode="34">
<Feature>
  <Name className="java.lang.String">length</Name>
  <Value className="java.lang.String">1</Value>
</Feature>
<Feature>
  <Name className="java.lang.String">string</Name>
  <Value className="java.lang.String">'</Value>
</Feature>
<Feature>
  <Name className="java.lang.String">category</Name>
  <Value className="java.lang.String">''</Value>
</Feature>
<Feature>
  <Name className="java.lang.String">kind</Name>
  <Value className="java.lang.String">punctuation</Value>
</Feature>
</Annotation>
<Annotation Id="204" Type="Token" StartNode="40" EndNode="41">
<Feature>
  <Name className="java.lang.String">length</Name>
  <Value className="java.lang.String">1</Value>
</Feature>
<Feature>
  <Name className="java.lang.String">string</Name>
  <Value className="java.lang.String">,</Value>
</Feature>
<Feature>
  <Name className="java.lang.String">category</Name>
  <Value className="java.lang.String">,</Value>
</Feature>
<Feature>
  <Name className="java.lang.String">kind</Name>
  <Value className="java.lang.String">punctuation</Value>
</Feature>
</Annotation>
<Annotation Id="205" Type="SpaceToken" StartNode="41" EndNode="42">
<Feature>
  <Name className="java.lang.String">string</Name>
  <Value className="java.lang.String"> </Value>
</Feature>
<Feature>
  <Name className="java.lang.String">length</Name>
  <Value className="java.lang.String">1</Value>
</Feature>
<Feature>
  <Name className="java.lang.String">kind</Name>
  <Value className="java.lang.String">space</Value>
</Feature>
</Annotation>
<Annotation Id="206" Type="Token" StartNode="42" EndNode="45">
<Feature>
  <Name className="java.lang.String">length</Name>
  <Value className="java.lang.String">3</Value>
</Feature>
<Feature>
  <Name className="java.lang.String">orth</Name>
  <Value className="java.lang.String">lowercase</Value>
</Feature>
<Feature>
  <Name className="java.lang.String">string</Name>
  <Value className="java.lang.String">que</Value>
</Feature>
<Feature>
  <Name className="java.lang.String">category</Name>
  <Value className="java.lang.String">FW</Value>
</Feature>
<Feature>
  <Name className="java.lang.String">kind</Name>
  <Value className="java.lang.String">word</Value>
</Feature>
</Annotation>
<Annotation Id="207" Type="SpaceToken" StartNode="45" EndNode="46">
<Feature>
  <Name className="java.lang.String">string</Name>
  <Value className="java.lang.String"> </Value>
</Feature>
<Feature>
  <Name className="java.lang.String">length</Name>
  <Value className="java.lang.String">1</Value>
</Feature>
<Feature>
  <Name className="java.lang.String">kind</Name>
  <Value className="java.lang.String">space</Value>
</Feature>
</Annotation>
<Annotation Id="208" Type="Token" StartNode="46" EndNode="51">
<Feature>
  <Name className="java.lang.String">length</Name>
  <Value className="java.lang.String">5</Value>
</Feature>
<Feature>
  <Name className="java.lang.String">orth</Name>
  <Value className="java.lang.String">lowercase</Value>
</Feature>
<Feature>
  <Name className="java.lang.String">origString</Name>
  <Value className="java.lang.String">parla</Value>
</Feature>
<Feature>
  <Name className="java.lang.String">string</Name>
  <Value className="java.lang.String">parla</Value>
</Feature>
<Feature>
  <Name className="java.lang.String">category</Name>
  <Value className="java.lang.String">FW</Value>
</Feature>
<Feature>
  <Name className="java.lang.String">kind</Name>
  <Value className="java.lang.String">word</Value>
</Feature>
</Annotation>
<Annotation Id="209" Type="SpaceToken" StartNode="51" EndNode="52">
<Feature>
  <Name className="java.lang.String">string</Name>
  <Value className="java.lang.String"> </Value>
</Feature>
<Feature>
  <Name className="java.lang.String">length</Name>
  <Value className="java.lang.String">1</Value>
</Feature>
<Feature>
  <Name className="java.lang.String">kind</Name>
  <Value className="java.lang.String">space</Value>
</Feature>
</Annotation>
<Annotation Id="210" Type="Token" StartNode="52" EndNode="54">
<Feature>
  <Name className="java.lang.String">length</Name>
  <Value className="java.lang.String">2</Value>
</Feature>
<Feature>
  <Name className="java.lang.String">orth</Name>
  <Value className="java.lang.String">lowercase</Value>
</Feature>
<Feature>
  <Name className="java.lang.String">string</Name>
  <Value className="java.lang.String">de</Value>
</Feature>
<Feature>
  <Name className="java.lang.String">category</Name>
  <Value className="java.lang.String">FW</Value>
</Feature>
<Feature>
  <Name className="java.lang.String">kind</Name>
  <Value className="java.lang.String">word</Value>
</Feature>
</Annotation>
<Annotation Id="211" Type="SpaceToken" StartNode="54" EndNode="55">
<Feature>
  <Name className="java.lang.String">string</Name>
  <Value className="java.lang.String"> </Value>
</Feature>
<Feature>
  <Name className="java.lang.String">length</Name>
  <Value className="java.lang.String">1</Value>
</Feature>
<Feature>
  <Name className="java.lang.String">kind</Name>
  <Value className="java.lang.String">space</Value>
</Feature>
</Annotation>
<Annotation Id="212" Type="Token" StartNode="55" EndNode="63">
<Feature>
  <Name className="java.lang.String">length</Name>
  <Value className="java.lang.String">8</Value>
</Feature>
<Feature>
  <Name className="java.lang.String">orth</Name>
  <Value className="java.lang.String">lowercase</Value>
</Feature>
<Feature>
  <Name className="java.lang.String">origString</Name>
  <Value className="java.lang.String">feixisme</Value>
</Feature>
<Feature>
  <Name className="java.lang.String">string</Name>
  <Value className="java.lang.String">feixisme</Value>
</Feature>
<Feature>
  <Name className="java.lang.String">category</Name>
  <Value className="java.lang.String">FW</Value>
</Feature>
<Feature>
  <Name className="java.lang.String">kind</Name>
  <Value className="java.lang.String">word</Value>
</Feature>
</Annotation>
<Annotation Id="213" Type="SpaceToken" StartNode="63" EndNode="64">
<Feature>
  <Name className="java.lang.String">string</Name>
  <Value className="java.lang.String"> </Value>
</Feature>
<Feature>
  <Name className="java.lang.String">length</Name>
  <Value className="java.lang.String">1</Value>
</Feature>
<Feature>
  <Name className="java.lang.String">kind</Name>
  <Value className="java.lang.String">space</Value>
</Feature>
</Annotation>
<Annotation Id="214" Type="Token" StartNode="64" EndNode="65">
<Feature>
  <Name className="java.lang.String">length</Name>
  <Value className="java.lang.String">1</Value>
</Feature>
<Feature>
  <Name className="java.lang.String">orth</Name>
  <Value className="java.lang.String">lowercase</Value>
</Feature>
<Feature>
  <Name className="java.lang.String">string</Name>
  <Value className="java.lang.String">a</Value>
</Feature>
<Feature>
  <Name className="java.lang.String">category</Name>
  <Value className="java.lang.String">FW</Value>
</Feature>
<Feature>
  <Name className="java.lang.String">kind</Name>
  <Value className="java.lang.String">word</Value>
</Feature>
</Annotation>
<Annotation Id="215" Type="SpaceToken" StartNode="65" EndNode="66">
<Feature>
  <Name className="java.lang.String">string</Name>
  <Value className="java.lang.String"> </Value>
</Feature>
<Feature>
  <Name className="java.lang.String">length</Name>
  <Value className="java.lang.String">1</Value>
</Feature>
<Feature>
  <Name className="java.lang.String">kind</Name>
  <Value className="java.lang.String">space</Value>
</Feature>
</Annotation>
<Annotation Id="216" Type="Token" StartNode="66" EndNode="68">
<Feature>
  <Name className="java.lang.String">length</Name>
  <Value className="java.lang.String">2</Value>
</Feature>
<Feature>
  <Name className="java.lang.String">orth</Name>
  <Value className="java.lang.String">lowercase</Value>
</Feature>
<Feature>
  <Name className="java.lang.String">string</Name>
  <Value className="java.lang.String">la</Value>
</Feature>
<Feature>
  <Name className="java.lang.String">category</Name>
  <Value className="java.lang.String">FW</Value>
</Feature>
<Feature>
  <Name className="java.lang.String">kind</Name>
  <Value className="java.lang.String">word</Value>
</Feature>
</Annotation>
<Annotation Id="217" Type="SpaceToken" StartNode="68" EndNode="69">
<Feature>
  <Name className="java.lang.String">string</Name>
  <Value className="java.lang.String"> </Value>
</Feature>
<Feature>
  <Name className="java.lang.String">length</Name>
  <Value className="java.lang.String">1</Value>
</Feature>
<Feature>
  <Name className="java.lang.String">kind</Name>
  <Value className="java.lang.String">space</Value>
</Feature>
</Annotation>
<Annotation Id="218" Type="Token" StartNode="69" EndNode="75">
<Feature>
  <Name className="java.lang.String">length</Name>
  <Value className="java.lang.String">6</Value>
</Feature>
<Feature>
  <Name className="java.lang.String">orth</Name>
  <Value className="java.lang.String">lowercase</Value>
</Feature>
<Feature>
  <Name className="java.lang.String">origString</Name>
  <Value className="java.lang.String">vegada</Value>
</Feature>
<Feature>
  <Name className="java.lang.String">string</Name>
  <Value className="java.lang.String">vegada</Value>
</Feature>
<Feature>
  <Name className="java.lang.String">category</Name>
  <Value className="java.lang.String">FW</Value>
</Feature>
<Feature>
  <Name className="java.lang.String">kind</Name>
  <Value className="java.lang.String">word</Value>
</Feature>
</Annotation>
<Annotation Id="219" Type="SpaceToken" StartNode="75" EndNode="76">
<Feature>
  <Name className="java.lang.String">string</Name>
  <Value className="java.lang.String"> </Value>
</Feature>
<Feature>
  <Name className="java.lang.String">length</Name>
  <Value className="java.lang.String">1</Value>
</Feature>
<Feature>
  <Name className="java.lang.String">kind</Name>
  <Value className="java.lang.String">space</Value>
</Feature>
</Annotation>
<Annotation Id="220" Type="Token" StartNode="76" EndNode="79">
<Feature>
  <Name className="java.lang.String">length</Name>
  <Value className="java.lang.String">3</Value>
</Feature>
<Feature>
  <Name className="java.lang.String">orth</Name>
  <Value className="java.lang.String">lowercase</Value>
</Feature>
<Feature>
  <Name className="java.lang.String">string</Name>
  <Value className="java.lang.String">que</Value>
</Feature>
<Feature>
  <Name className="java.lang.String">category</Name>
  <Value className="java.lang.String">FW</Value>
</Feature>
<Feature>
  <Name className="java.lang.String">kind</Name>
  <Value className="java.lang.String">word</Value>
</Feature>
</Annotation>
<Annotation Id="221" Type="SpaceToken" StartNode="79" EndNode="80">
<Feature>
  <Name className="java.lang.String">string</Name>
  <Value className="java.lang.String"> </Value>
</Feature>
<Feature>
  <Name className="java.lang.String">length</Name>
  <Value className="java.lang.String">1</Value>
</Feature>
<Feature>
  <Name className="java.lang.String">kind</Name>
  <Value className="java.lang.String">space</Value>
</Feature>
</Annotation>
<Annotation Id="222" Type="Token" StartNode="80" EndNode="87">
<Feature>
  <Name className="java.lang.String">length</Name>
  <Value className="java.lang.String">7</Value>
</Feature>
<Feature>
  <Name className="java.lang.String">orth</Name>
  <Value className="java.lang.String">lowercase</Value>
</Feature>
<Feature>
  <Name className="java.lang.String">origString</Name>
  <Value className="java.lang.String">recolza</Value>
</Feature>
<Feature>
  <Name className="java.lang.String">string</Name>
  <Value className="java.lang.String">recolza</Value>
</Feature>
<Feature>
  <Name className="java.lang.String">category</Name>
  <Value className="java.lang.String">FW</Value>
</Feature>
<Feature>
  <Name className="java.lang.String">kind</Name>
  <Value className="java.lang.String">word</Value>
</Feature>
</Annotation>
<Annotation Id="223" Type="SpaceToken" StartNode="87" EndNode="88">
<Feature>
  <Name className="java.lang.String">string</Name>
  <Value className="java.lang.String"> </Value>
</Feature>
<Feature>
  <Name className="java.lang.String">length</Name>
  <Value className="java.lang.String">1</Value>
</Feature>
<Feature>
  <Name className="java.lang.String">kind</Name>
  <Value className="java.lang.String">space</Value>
</Feature>
</Annotation>
<Annotation Id="224" Type="Token" StartNode="88" EndNode="91">
<Feature>
  <Name className="java.lang.String">length</Name>
  <Value className="java.lang.String">3</Value>
</Feature>
<Feature>
  <Name className="java.lang.String">orth</Name>
  <Value className="java.lang.String">lowercase</Value>
</Feature>
<Feature>
  <Name className="java.lang.String">string</Name>
  <Value className="java.lang.String">que</Value>
</Feature>
<Feature>
  <Name className="java.lang.String">category</Name>
  <Value className="java.lang.String">FW</Value>
</Feature>
<Feature>
  <Name className="java.lang.String">kind</Name>
  <Value className="java.lang.String">word</Value>
</Feature>
</Annotation>
<Annotation Id="225" Type="SpaceToken" StartNode="91" EndNode="92">
<Feature>
  <Name className="java.lang.String">string</Name>
  <Value className="java.lang.String"> </Value>
</Feature>
<Feature>
  <Name className="java.lang.String">length</Name>
  <Value className="java.lang.String">1</Value>
</Feature>
<Feature>
  <Name className="java.lang.String">kind</Name>
  <Value className="java.lang.String">space</Value>
</Feature>
</Annotation>
<Annotation Id="226" Type="Token" StartNode="92" EndNode="97">
<Feature>
  <Name className="java.lang.String">length</Name>
  <Value className="java.lang.String">5</Value>
</Feature>
<Feature>
  <Name className="java.lang.String">orth</Name>
  <Value className="java.lang.String">lowercase</Value>
</Feature>
<Feature>
  <Name className="java.lang.String">origString</Name>
  <Value className="java.lang.String">fotin</Value>
</Feature>
<Feature>
  <Name className="java.lang.String">string</Name>
  <Value className="java.lang.String">fotin</Value>
</Feature>
<Feature>
  <Name className="java.lang.String">category</Name>
  <Value className="java.lang.String">FW</Value>
</Feature>
<Feature>
  <Name className="java.lang.String">kind</Name>
  <Value className="java.lang.String">word</Value>
</Feature>
</Annotation>
<Annotation Id="227" Type="SpaceToken" StartNode="97" EndNode="98">
<Feature>
  <Name className="java.lang.String">string</Name>
  <Value className="java.lang.String"> </Value>
</Feature>
<Feature>
  <Name className="java.lang.String">length</Name>
  <Value className="java.lang.String">1</Value>
</Feature>
<Feature>
  <Name className="java.lang.String">kind</Name>
  <Value className="java.lang.String">space</Value>
</Feature>
</Annotation>
<Annotation Id="228" Type="Token" StartNode="98" EndNode="102">
<Feature>
  <Name className="java.lang.String">length</Name>
  <Value className="java.lang.String">4</Value>
</Feature>
<Feature>
  <Name className="java.lang.String">orth</Name>
  <Value className="java.lang.String">lowercase</Value>
</Feature>
<Feature>
  <Name className="java.lang.String">string</Name>
  <Value className="java.lang.String">fora</Value>
</Feature>
<Feature>
  <Name className="java.lang.String">category</Name>
  <Value className="java.lang.String">FW</Value>
</Feature>
<Feature>
  <Name className="java.lang.String">kind</Name>
  <Value className="java.lang.String">word</Value>
</Feature>
</Annotation>
<Annotation Id="229" Type="SpaceToken" StartNode="102" EndNode="103">
<Feature>
  <Name className="java.lang.String">string</Name>
  <Value className="java.lang.String"> </Value>
</Feature>
<Feature>
  <Name className="java.lang.String">length</Name>
  <Value className="java.lang.String">1</Value>
</Feature>
<Feature>
  <Name className="java.lang.String">kind</Name>
  <Value className="java.lang.String">space</Value>
</Feature>
</Annotation>
<Annotation Id="230" Type="Token" StartNode="103" EndNode="104">
<Feature>
  <Name className="java.lang.String">length</Name>
  <Value className="java.lang.String">1</Value>
</Feature>
<Feature>
  <Name className="java.lang.String">orth</Name>
  <Value className="java.lang.String">lowercase</Value>
</Feature>
<Feature>
  <Name className="java.lang.String">string</Name>
  <Value className="java.lang.String">a</Value>
</Feature>
<Feature>
  <Name className="java.lang.String">category</Name>
  <Value className="java.lang.String">DT</Value>
</Feature>
<Feature>
  <Name className="java.lang.String">kind</Name>
  <Value className="java.lang.String">word</Value>
</Feature>
</Annotation>
<Annotation Id="231" Type="SpaceToken" StartNode="104" EndNode="105">
<Feature>
  <Name className="java.lang.String">string</Name>
  <Value className="java.lang.String"> </Value>
</Feature>
<Feature>
  <Name className="java.lang.String">length</Name>
  <Value className="java.lang.String">1</Value>
</Feature>
<Feature>
  <Name className="java.lang.String">kind</Name>
  <Value className="java.lang.String">space</Value>
</Feature>
</Annotation>
<Annotation Id="232" Type="Token" StartNode="105" EndNode="107">
<Feature>
  <Name className="java.lang.String">length</Name>
  <Value className="java.lang.String">2</Value>
</Feature>
<Feature>
  <Name className="java.lang.String">string</Name>
  <Value className="java.lang.String">35</Value>
</Feature>
<Feature>
  <Name className="java.lang.String">category</Name>
  <Value className="java.lang.String">CD</Value>
</Feature>
<Feature>
  <Name className="java.lang.String">kind</Name>
  <Value className="java.lang.String">number</Value>
</Feature>
</Annotation>
<Annotation Id="233" Type="SpaceToken" StartNode="107" EndNode="108">
<Feature>
  <Name className="java.lang.String">string</Name>
  <Value className="java.lang.String"> </Value>
</Feature>
<Feature>
  <Name className="java.lang.String">length</Name>
  <Value className="java.lang.String">1</Value>
</Feature>
<Feature>
  <Name className="java.lang.String">kind</Name>
  <Value className="java.lang.String">space</Value>
</Feature>
</Annotation>
<Annotation Id="234" Type="Token" StartNode="108" EndNode="115">
<Feature>
  <Name className="java.lang.String">length</Name>
  <Value className="java.lang.String">7</Value>
</Feature>
<Feature>
  <Name className="java.lang.String">orth</Name>
  <Value className="java.lang.String">lowercase</Value>
</Feature>
<Feature>
  <Name className="java.lang.String">origString</Name>
  <Value className="java.lang.String">persone</Value>
</Feature>
<Feature>
  <Name className="java.lang.String">string</Name>
  <Value className="java.lang.String">persona</Value>
</Feature>
<Feature>
  <Name className="java.lang.String">category</Name>
  <Value className="java.lang.String">NN</Value>
</Feature>
<Feature>
  <Name className="java.lang.String">kind</Name>
  <Value className="java.lang.String">word</Value>
</Feature>
</Annotation>
<Annotation Id="235" Type="Token" StartNode="115" EndNode="116">
<Feature>
  <Name className="java.lang.String">length</Name>
  <Value className="java.lang.String">1</Value>
</Feature>
<Feature>
  <Name className="java.lang.String">string</Name>
  <Value className="java.lang.String">…</Value>
</Feature>
<Feature>
  <Name className="java.lang.String">category</Name>
  <Value className="java.lang.String">.</Value>
</Feature>
<Feature>
  <Name className="java.lang.String">kind</Name>
  <Value className="java.lang.String">punctuation</Value>
</Feature>
</Annotation>
<Annotation Id="236" Type="SpaceToken" StartNode="116" EndNode="117">
<Feature>
  <Name className="java.lang.String">string</Name>
  <Value className="java.lang.String"> </Value>
</Feature>
<Feature>
  <Name className="java.lang.String">length</Name>
  <Value className="java.lang.String">1</Value>
</Feature>
<Feature>
  <Name className="java.lang.String">kind</Name>
  <Value className="java.lang.String">space</Value>
</Feature>
</Annotation>
<Annotation Id="251" Type="UserID" StartNode="35" EndNode="40">
<Feature>
  <Name className="java.lang.String">length</Name>
  <Value className="java.lang.Long">5</Value>
</Feature>
<Feature>
  <Name className="java.lang.String">rule</Name>
  <Value className="java.lang.String">UserID</Value>
</Feature>
<Feature>
  <Name className="java.lang.String">replaced</Name>
  <Value className="java.lang.Integer">2</Value>
</Feature>
<Feature>
  <Name className="java.lang.String">string</Name>
  <Value className="java.lang.String">@sport</Value>
</Feature>
<Feature>
  <Name className="java.lang.String">user</Name>
  <Value className="java.lang.String">sport</Value>
</Feature>
<Feature>
  <Name className="java.lang.String">kind</Name>
  <Value className="java.lang.String">UserID</Value>
</Feature>
</Annotation>
<Annotation Id="252" Type="UserMention" StartNode="34" EndNode="40">
<Feature>
  <Name className="java.lang.String">length</Name>
  <Value className="java.lang.Long">5</Value>
</Feature>
<Feature>
  <Name className="java.lang.String">rule</Name>
  <Value className="java.lang.String">UserID</Value>
</Feature>
<Feature>
  <Name className="java.lang.String">replaced</Name>
  <Value className="java.lang.Integer">2</Value>
</Feature>
<Feature>
  <Name className="java.lang.String">string</Name>
  <Value className="java.lang.String">@sport</Value>
</Feature>
<Feature>
  <Name className="java.lang.String">user</Name>
  <Value className="java.lang.String">sport</Value>
</Feature>
<Feature>
  <Name className="java.lang.String">kind</Name>
  <Value className="java.lang.String">UserID</Value>
</Feature>
</Annotation>
<Annotation Id="253" Type="Token" StartNode="34" EndNode="40">
<Feature>
  <Name className="java.lang.String">length</Name>
  <Value className="java.lang.Long">6</Value>
</Feature>
<Feature>
  <Name className="java.lang.String">rule</Name>
  <Value className="java.lang.String">UserID</Value>
</Feature>
<Feature>
  <Name className="java.lang.String">category</Name>
  <Value className="java.lang.String">USR</Value>
</Feature>
<Feature>
  <Name className="java.lang.String">string</Name>
  <Value className="java.lang.String">sport</Value>
</Feature>
<Feature>
  <Name className="java.lang.String">kind</Name>
  <Value className="java.lang.String">word</Value>
</Feature>
</Annotation>
<Annotation Id="254" Type="Token" StartNode="117" EndNode="140">
<Feature>
  <Name className="java.lang.String">string</Name>
  <Value className="java.lang.String">https://t.co/Cmttd1kJx0</Value>
</Feature>
<Feature>
  <Name className="java.lang.String">kind</Name>
  <Value className="java.lang.String">URL</Value>
</Feature>
<Feature>
  <Name className="java.lang.String">temp_category</Name>
  <Value className="java.lang.String">NN</Value>
</Feature>
<Feature>
  <Name className="java.lang.String">length</Name>
  <Value className="java.lang.Long">23</Value>
</Feature>
<Feature>
  <Name className="java.lang.String">rule</Name>
  <Value className="java.lang.String">URL</Value>
</Feature>
<Feature>
  <Name className="java.lang.String">replaced</Name>
  <Value className="java.lang.Integer">12</Value>
</Feature>
<Feature>
  <Name className="java.lang.String">category</Name>
  <Value className="java.lang.String">URL</Value>
</Feature>
</Annotation>
<Annotation Id="255" Type="URL" StartNode="117" EndNode="140">
<Feature>
  <Name className="java.lang.String">string</Name>
  <Value className="java.lang.String">https://t.co/Cmttd1kJx0</Value>
</Feature>
<Feature>
  <Name className="java.lang.String">kind</Name>
  <Value className="java.lang.String">URL</Value>
</Feature>
<Feature>
  <Name className="java.lang.String">temp_category</Name>
  <Value className="java.lang.String">NN</Value>
</Feature>
<Feature>
  <Name className="java.lang.String">length</Name>
  <Value className="java.lang.Long">23</Value>
</Feature>
<Feature>
  <Name className="java.lang.String">rule</Name>
  <Value className="java.lang.String">URL</Value>
</Feature>
<Feature>
  <Name className="java.lang.String">replaced</Name>
  <Value className="java.lang.Integer">12</Value>
</Feature>
<Feature>
  <Name className="java.lang.String">category</Name>
  <Value className="java.lang.String">URL</Value>
</Feature>
</Annotation>
</AnnotationSet>

<!-- Named annotation set -->

<AnnotationSet Name="Original markups">
<Annotation Id="0" Type="Tweet" StartNode="0" EndNode="140">
<Feature>
  <Name className="java.lang.String">extended_tweet</Name>
  <Value className="gate.corpora.ObjectWrapper"><![CDATA[<?xml version='1.1'?><gate.corpora.ObjectWrapper><value class="gate.util.SimpleFeatureMapImpl" serialization="custom"><gate.util.SimpleMapImpl><default><capacity>3</capacity><count>3</count><theKeys><string>entities</string><string>full_text</string><string>display_text_range</string></theKeys><theValues><gate.util.SimpleFeatureMapImpl serialization="custom"><gate.util.SimpleMapImpl><default><capacity>6</capacity><count>4</count><theKeys><string>urls</string><string>hashtags</string><string>user_mentions</string><string>symbols</string><null/><null/></theKeys><theValues><list><gate.util.SimpleFeatureMapImpl serialization="custom"><gate.util.SimpleMapImpl><default><capacity>6</capacity><count>4</count><theKeys><string>display_url</string><string>indices</string><string>expanded_url</string><string>url</string><null/><null/></theKeys><theValues><string>twitter.com/LluisMascaro/s…</string><list><long>127</long><long>150</long></list><string>https://twitter.com/LluisMascaro/status/926371590694195201</string><string>https://t.co/dJd0JGCIbq</string><null/><null/></theValues></default></gate.util.SimpleMapImpl></gate.util.SimpleFeatureMapImpl></list><list/><list><gate.util.SimpleFeatureMapImpl serialization="custom"><gate.util.SimpleMapImpl><default><capacity>6</capacity><count>5</count><theKeys><string>indices</string><string>screen_name</string><string>id_str</string><string>name</string><string>id</string><null/></theKeys><theValues><list><long>34</long><long>40</long></list><string>sport</string><string>19343904</string><string>Diario SPORT</string><long>19343904</long><null/></theValues></default></gate.util.SimpleMapImpl></gate.util.SimpleFeatureMapImpl></list><list/><null/><null/></theValues></default></gate.util.SimpleMapImpl></gate.util.SimpleFeatureMapImpl><string>Aquest es el director adjunt de l'@sport, que parla de feixisme a la vegada que recolza que fotin fora a 35 persones del diari https://t.co/dJd0JGCIbq</string><list><long>0</long><long>126</long></list></theValues></default></gate.util.SimpleMapImpl></value></gate.corpora.ObjectWrapper>]]></Value>
</Feature>
<Feature>
  <Name className="java.lang.String">quoted_status</Name>
  <Value className="gate.corpora.ObjectWrapper"><![CDATA[<?xml version='1.1'?><gate.corpora.ObjectWrapper><value class="gate.util.SimpleFeatureMapImpl" serialization="custom"><gate.util.SimpleMapImpl><default><capacity>48</capacity><count>31</count><theKeys><string>extended_tweet</string><string>in_reply_to_status_id_str</string><string>in_reply_to_status_id</string><string>created_at</string><string>in_reply_to_user_id_str</string><string>source</string><string>quoted_status_id</string><string>retweet_count</string><string>retweeted</string><string>geo</string><string>filter_level</string><string>in_reply_to_screen_name</string><string>is_quote_status</string><string>id_str</string><string>in_reply_to_user_id</string><string>favorite_count</string><string>id</string><string>text</string><string>place</string><string>lang</string><string>quote_count</string><string>favorited</string><string>possibly_sensitive</string><string>coordinates</string><string>truncated</string><string>reply_count</string><string>entities</string><string>display_text_range</string><string>quoted_status_id_str</string><string>contributors</string><string>user</string><null/><null/><null/><null/><null/><null/><null/><null/><null/><null/><null/><null/><null/><null/><null/><null/><null/></theKeys><theValues><gate.util.SimpleFeatureMapImpl serialization="custom"><gate.util.SimpleMapImpl><default><capacity>3</capacity><count>3</count><theKeys><string>entities</string><string>full_text</string><string>display_text_range</string></theKeys><theValues><gate.util.SimpleFeatureMapImpl serialization="custom"><gate.util.SimpleMapImpl><default><capacity>6</capacity><count>4</count><theKeys><string>urls</string><string>hashtags</string><string>user_mentions</string><string>symbols</string><null/><null/></theKeys><theValues><list><gate.util.SimpleFeatureMapImpl serialization="custom"><gate.util.SimpleMapImpl><default><capacity>6</capacity><count>4</count><theKeys><string>display_url</string><string>indices</string><string>expanded_url</string><string>url</string><null/><null/></theKeys><theValues><string>twitter.com/RamonAndreuCau…</string><list><long>141</long><long>164</long></list><string>https://twitter.com/RamonAndreuCauf/status/926362538610225152</string><string>https://t.co/HfTnDwHh6S</string><null/><null/></theValues></default></gate.util.SimpleMapImpl></gate.util.SimpleFeatureMapImpl></list><list/><list/><list/><null/><null/></theValues></default></gate.util.SimpleMapImpl></gate.util.SimpleFeatureMapImpl><string>S'ha de lluitar de totes les maneres possibles contra el feixisme. No es pot fer veure que no passa res. Perque sí passa. I molt. Llibertat! https://t.co/HfTnDwHh6S</string><list><long>0</long><long>140</long></list></theValues></default></gate.util.SimpleMapImpl></gate.util.SimpleFeatureMapImpl><null/><null/><string>Fri Nov 03 08:52:53 +0000 2017</string><null/><string>&lt;a href="https://about.twitter.com/products/tweetdeck" rel="nofollow">TweetDeck&lt;/a></string><long>926362538610225152</long><long>4</long><boolean>false</boolean><null/><string>low</string><null/><boolean>true</boolean><string>926371590694195201</string><null/><long>15</long><long>926371590694195201</long><string>S'ha de lluitar de totes les maneres possibles contra el feixisme. No es pot fer veure que no passa res. Perque sí… https://t.co/NNNrjKFaQP</string><null/><string>und</string><long>1</long><boolean>false</boolean><boolean>false</boolean><null/><boolean>true</boolean><long>26</long><gate.util.SimpleFeatureMapImpl serialization="custom"><gate.util.SimpleMapImpl><default><capacity>6</capacity><count>4</count><theKeys><string>urls</string><string>hashtags</string><string>user_mentions</string><string>symbols</string><null/><null/></theKeys><theValues><list><gate.util.SimpleFeatureMapImpl serialization="custom"><gate.util.SimpleMapImpl><default><capacity>6</capacity><count>4</count><theKeys><string>display_url</string><string>indices</string><string>expanded_url</string><string>url</string><null/><null/></theKeys><theValues><string>twitter.com/i/web/status/9…</string><list><long>116</long><long>139</long></list><string>https://twitter.com/i/web/status/926371590694195201</string><string>https://t.co/NNNrjKFaQP</string><null/><null/></theValues></default></gate.util.SimpleMapImpl></gate.util.SimpleFeatureMapImpl></list><list/><list/><list/><null/><null/></theValues></default></gate.util.SimpleMapImpl></gate.util.SimpleFeatureMapImpl><list><long>0</long><long>140</long></list><string>926362538610225152</string><null/><gate.util.SimpleFeatureMapImpl serialization="custom"><gate.util.SimpleMapImpl><default><capacity>48</capacity><count>39</count><theKeys><string>utc_offset</string><string>friends_count</string><string>profile_image_url_https</string><string>listed_count</string><string>profile_background_image_url</string><string>default_profile_image</string><string>favourites_count</string><string>description</string><string>created_at</string><string>is_translator</string><string>profile_background_image_url_https</string><string>protected</string><string>screen_name</string><string>id_str</string><string>profile_link_color</string><string>translator_type</string><string>id</string><string>geo_enabled</string><string>profile_background_color</string><string>lang</string><string>profile_sidebar_border_color</string><string>profile_text_color</string><string>verified</string><string>profile_image_url</string><string>time_zone</string><string>url</string><string>contributors_enabled</string><string>profile_background_tile</string><string>profile_banner_url</string><string>statuses_count</string><string>follow_request_sent</string><string>followers_count</string><string>profile_use_background_image</string><string>default_profile</string><string>following</string><string>name</string><string>location</string><string>profile_sidebar_fill_color</string><string>notifications</string><null/><null/><null/><null/><null/><null/><null/><null/><null/></theKeys><theValues><long>-28800</long><long>729</long><string>https://pbs.twimg.com/profile_images/839943685362044929/9S3_PvGg_normal.jpg</string><long>732</long><string>http://abs.twimg.com/images/themes/theme1/bg.png</string><boolean>false</boolean><long>43</long><string>Periodista 👨🏻‍💻Marido de Lluïsa 👸Nadador 🏊🏽</string><string>Wed Jan 20 20:02:25 +0000 2010</string><boolean>false</boolean><string>https://abs.twimg.com/images/themes/theme1/bg.png</string><boolean>false</boolean><string>LluisMascaro</string><string>106818870</string><string>1DA1F2</string><string>none</string><long>106818870</long><boolean>false</boolean><string>C0DEED</string><string>es</string><string>C0DEED</string><string>333333</string><boolean>false</boolean><string>http://pbs.twimg.com/profile_images/839943685362044929/9S3_PvGg_normal.jpg</string><string>Pacific Time (US &amp; Canada)</string><string>http://sport.es</string><boolean>false</boolean><boolean>false</boolean><string>https://pbs.twimg.com/profile_banners/106818870/1487681348</string><long>5702</long><null/><long>57040</long><boolean>true</boolean><boolean>true</boolean><null/><string>Lluís Mascaró</string><string>Barcelona</string><string>DDEEF6</string><null/><null/><null/><null/><null/><null/><null/><null/><null/><null/></theValues></default></gate.util.SimpleMapImpl></gate.util.SimpleFeatureMapImpl><null/><null/><null/><null/><null/><null/><null/><null/><null/><null/><null/><null/><null/><null/><null/><null/><null/></theValues></default></gate.util.SimpleMapImpl></value></gate.corpora.ObjectWrapper>]]></Value>
</Feature>
<Feature>
  <Name className="java.lang.String">created_at</Name>
  <Value className="java.lang.String">Thu Nov 30 12:02:39 +0000 2017</Value>
</Feature>
<Feature>
  <Name className="java.lang.String">source</Name>
  <Value className="java.lang.String">&lt;a href="http://twitter.com/download/android" rel="nofollow">Twitter for Android&lt;/a></Value>
</Feature>
<Feature>
  <Name className="java.lang.String">quoted_status_id</Name>
  <Value className="java.lang.Long">926371590694195201</Value>
</Feature>
<Feature>
  <Name className="java.lang.String">retweet_count</Name>
  <Value className="java.lang.Long">0</Value>
</Feature>
<Feature>
  <Name className="java.lang.String">retweeted</Name>
  <Value className="java.lang.Boolean">false</Value>
</Feature>
<Feature>
  <Name className="java.lang.String">filter_level</Name>
  <Value className="java.lang.String">low</Value>
</Feature>
<Feature>
  <Name className="java.lang.String">is_quote_status</Name>
  <Value className="java.lang.Boolean">true</Value>
</Feature>
<Feature>
  <Name className="java.lang.String">id_str</Name>
  <Value className="java.lang.String">936203820434116608</Value>
</Feature>
<Feature>
  <Name className="java.lang.String">favorite_count</Name>
  <Value className="java.lang.Long">0</Value>
</Feature>
<Feature>
  <Name className="java.lang.String">id</Name>
  <Value className="java.lang.Long">936203820434116608</Value>
</Feature>
<Feature>
  <Name className="java.lang.String">place</Name>
  <Value className="gate.corpora.ObjectWrapper"><![CDATA[<?xml version='1.1'?><gate.corpora.ObjectWrapper><value class="gate.util.SimpleFeatureMapImpl" serialization="custom"><gate.util.SimpleMapImpl><default><capacity>12</capacity><count>9</count><theKeys><string>country_code</string><string>country</string><string>full_name</string><string>bounding_box</string><string>place_type</string><string>name</string><string>attributes</string><string>id</string><string>url</string><null/><null/><null/></theKeys><theValues><string>ES</string><string>España</string><string>Barcelona, España</string><gate.util.SimpleFeatureMapImpl serialization="custom"><gate.util.SimpleMapImpl><default><capacity>3</capacity><count>2</count><theKeys><string>coordinates</string><string>type</string><null/></theKeys><theValues><list><list><list><double>2.052477</double><double>41.317048</double></list><list><double>2.052477</double><double>41.468266</double></list><list><double>2.229978</double><double>41.468266</double></list><list><double>2.229978</double><double>41.317048</double></list></list></list><string>Polygon</string><null/></theValues></default></gate.util.SimpleMapImpl></gate.util.SimpleFeatureMapImpl><string>city</string><string>Barcelona</string><gate.util.SimpleFeatureMapImpl serialization="custom"><gate.util.SimpleMapImpl><default><capacity>3</capacity><count>0</count><theKeys><null/><null/><null/></theKeys><theValues><null/><null/><null/></theValues></default></gate.util.SimpleMapImpl></gate.util.SimpleFeatureMapImpl><string>1a27537478dd8e38</string><string>https://api.twitter.com/1.1/geo/id/1a27537478dd8e38.json</string><null/><null/><null/></theValues></default></gate.util.SimpleMapImpl></value></gate.corpora.ObjectWrapper>]]></Value>
</Feature>
<Feature>
  <Name className="java.lang.String">lang</Name>
  <Value className="java.lang.String">und</Value>
</Feature>
<Feature>
  <Name className="java.lang.String">quote_count</Name>
  <Value className="java.lang.Long">0</Value>
</Feature>
<Feature>
  <Name className="java.lang.String">favorited</Name>
  <Value className="java.lang.Boolean">false</Value>
</Feature>
<Feature>
  <Name className="java.lang.String">possibly_sensitive</Name>
  <Value className="java.lang.Boolean">false</Value>
</Feature>
<Feature>
  <Name className="java.lang.String">truncated</Name>
  <Value className="java.lang.Boolean">true</Value>
</Feature>
<Feature>
  <Name className="java.lang.String">timestamp_ms</Name>
  <Value className="java.lang.String">1512043359274</Value>
</Feature>
<Feature>
  <Name className="java.lang.String">reply_count</Name>
  <Value className="java.lang.Long">0</Value>
</Feature>
<Feature>
  <Name className="java.lang.String">display_text_range</Name>
  <Value className="gate.corpora.ObjectWrapper"><![CDATA[<?xml version='1.1'?><gate.corpora.ObjectWrapper><value class="list"><long>0</long><long>140</long></value></gate.corpora.ObjectWrapper>]]></Value>
</Feature>
<Feature>
  <Name className="java.lang.String">quoted_status_id_str</Name>
  <Value className="java.lang.String">926371590694195201</Value>
</Feature>
<Feature>
  <Name className="java.lang.String">user</Name>
  <Value className="gate.corpora.ObjectWrapper"><![CDATA[<?xml version='1.1'?><gate.corpora.ObjectWrapper><value class="gate.util.SimpleFeatureMapImpl" serialization="custom"><gate.util.SimpleMapImpl><default><capacity>48</capacity><count>39</count><theKeys><string>utc_offset</string><string>friends_count</string><string>profile_image_url_https</string><string>listed_count</string><string>profile_background_image_url</string><string>default_profile_image</string><string>favourites_count</string><string>description</string><string>created_at</string><string>is_translator</string><string>profile_background_image_url_https</string><string>protected</string><string>screen_name</string><string>id_str</string><string>profile_link_color</string><string>translator_type</string><string>id</string><string>geo_enabled</string><string>profile_background_color</string><string>lang</string><string>profile_sidebar_border_color</string><string>profile_text_color</string><string>verified</string><string>profile_image_url</string><string>time_zone</string><string>url</string><string>contributors_enabled</string><string>profile_background_tile</string><string>profile_banner_url</string><string>statuses_count</string><string>follow_request_sent</string><string>followers_count</string><string>profile_use_background_image</string><string>default_profile</string><string>following</string><string>name</string><string>location</string><string>profile_sidebar_fill_color</string><string>notifications</string><null/><null/><null/><null/><null/><null/><null/><null/><null/></theKeys><theValues><long>3600</long><long>1194</long><string>https://pbs.twimg.com/profile_images/2621085898/s3x6i6ji4znhgxslx50e_normal.jpeg</string><long>189</long><string>http://pbs.twimg.com/profile_background_images/661309140/tpwaqdsvy3ok6n5ylxj5.jpeg</string><boolean>false</boolean><long>155</long><string>Periodista. Quan es pot</string><string>Thu Sep 23 17:06:13 +0000 2010</string><boolean>false</boolean><string>https://pbs.twimg.com/profile_background_images/661309140/tpwaqdsvy3ok6n5ylxj5.jpeg</string><boolean>false</boolean><string>Elwood_White</string><string>194191462</string><string>0084B4</string><string>none</string><long>194191462</long><boolean>true</boolean><string>022330</string><string>es</string><string>A8C7F7</string><string>333333</string><boolean>false</boolean><string>http://pbs.twimg.com/profile_images/2621085898/s3x6i6ji4znhgxslx50e_normal.jpeg</string><string>Madrid</string><string>http://sport.es</string><boolean>false</boolean><boolean>false</boolean><string>https://pbs.twimg.com/profile_banners/194191462/1477435227</string><long>40119</long><null/><long>4936</long><boolean>true</boolean><boolean>false</boolean><null/><string>Jordi Blanco Duch</string><string>Barcelona city</string><string>C0DFEC</string><null/><null/><null/><null/><null/><null/><null/><null/><null/><null/></theValues></default></gate.util.SimpleMapImpl></value></gate.corpora.ObjectWrapper>]]></Value>
</Feature>
</Annotation>
<Annotation Id="1" Type="urls" StartNode="117" EndNode="140">
<Feature>
  <Name className="java.lang.String">expanded_url</Name>
  <Value className="java.lang.String">https://twitter.com/i/web/status/936203820434116608</Value>
</Feature>
<Feature>
  <Name className="java.lang.String">display_url</Name>
  <Value className="java.lang.String">twitter.com/i/web/status/9…</Value>
</Feature>
<Feature>
  <Name className="java.lang.String">url</Name>
  <Value className="java.lang.String">https://t.co/Cmttd1kJx0</Value>
</Feature>
</Annotation>
<Annotation Id="2" Type="user_mentions" StartNode="34" EndNode="40">
<Feature>
  <Name className="java.lang.String">name</Name>
  <Value className="java.lang.String">Diario SPORT</Value>
</Feature>
<Feature>
  <Name className="java.lang.String">id</Name>
  <Value className="java.lang.Long">19343904</Value>
</Feature>
<Feature>
  <Name className="java.lang.String">screen_name</Name>
  <Value className="java.lang.String">sport</Value>
</Feature>
<Feature>
  <Name className="java.lang.String">id_str</Name>
  <Value className="java.lang.String">19343904</Value>
</Feature>
</Annotation>
</AnnotationSet>

</GateDocument>
