{"extended_entities":{"media":[{"display_url":"pic.twitter.com/K7fVqBIoNP","source_user_id":62986843,"type":"photo","media_url":"http://pbs.twimg.com/media/DPO7a_YXUAAvxFA.jpg","source_status_id":933295636509876226,"url":"https://t.co/K7fVqBIoNP","indices":[101,124],"sizes":{"small":{"w":680,"h":679,"resize":"fit"},"large":{"w":1079,"h":1078,"resize":"fit"},"thumb":{"w":150,"h":150,"resize":"crop"},"medium":{"w":1079,"h":1078,"resize":"fit"}},"id_str":"933295620160442368","expanded_url":"https://twitter.com/leonypacheco/status/933295636509876226/photo/1","source_status_id_str":"933295636509876226","media_url_https":"https://pbs.twimg.com/media/DPO7a_YXUAAvxFA.jpg","id":933295620160442368,"source_user_id_str":"62986843"}]},"metadata":{"result_type":"recent","iso_language_code":"pt"},"in_reply_to_status_id_str":null,"in_reply_to_status_id":null,"created_at":"Wed Nov 22 12:11:50 +0000 2017","in_reply_to_user_id_str":null,"source":"<a href=\"https://mobile.twitter.com\" rel=\"nofollow\">Twitter Lite<\/a>","retweeted_status":{"extended_entities":{"media":[{"display_url":"pic.twitter.com/K7fVqBIoNP","indices":[83,106],"sizes":{"small":{"w":680,"h":679,"resize":"fit"},"large":{"w":1079,"h":1078,"resize":"fit"},"thumb":{"w":150,"h":150,"resize":"crop"},"medium":{"w":1079,"h":1078,"resize":"fit"}},"id_str":"933295620160442368","expanded_url":"https://twitter.com/leonypacheco/status/933295636509876226/photo/1","media_url_https":"https://pbs.twimg.com/media/DPO7a_YXUAAvxFA.jpg","id":933295620160442368,"type":"photo","media_url":"http://pbs.twimg.com/media/DPO7a_YXUAAvxFA.jpg","url":"https://t.co/K7fVqBIoNP"}]},"metadata":{"result_type":"recent","iso_language_code":"pt"},"in_reply_to_status_id_str":null,"in_reply_to_status_id":null,"created_at":"Wed Nov 22 11:26:34 +0000 2017","in_reply_to_user_id_str":null,"source":"<a href=\"http://twitter.com/download/android\" rel=\"nofollow\">Twitter for Android<\/a>","retweet_count":12,"retweeted":false,"geo":null,"in_reply_to_screen_name":null,"is_quote_status":false,"id_str":"933295636509876226","in_reply_to_user_id":null,"favorite_count":24,"id":933295636509876226,"text":"Tenho gostos peculiares que pessoas normais não entenderiam...\n\n#ConteUmSegredoSeu https://t.co/K7fVqBIoNP","place":null,"lang":"pt","favorited":false,"possibly_sensitive":false,"coordinates":null,"truncated":false,"entities":{"urls":[],"hashtags":[{"indices":[64,82],"text":"ConteUmSegredoSeu"}],"media":[{"display_url":"pic.twitter.com/K7fVqBIoNP","indices":[83,106],"sizes":{"small":{"w":680,"h":679,"resize":"fit"},"large":{"w":1079,"h":1078,"resize":"fit"},"thumb":{"w":150,"h":150,"resize":"crop"},"medium":{"w":1079,"h":1078,"resize":"fit"}},"id_str":"933295620160442368","expanded_url":"https://twitter.com/leonypacheco/status/933295636509876226/photo/1","media_url_https":"https://pbs.twimg.com/media/DPO7a_YXUAAvxFA.jpg","id":933295620160442368,"type":"photo","media_url":"http://pbs.twimg.com/media/DPO7a_YXUAAvxFA.jpg","url":"https://t.co/K7fVqBIoNP"}],"user_mentions":[],"symbols":[]},"contributors":null,"user":{"utc_offset":-7200,"friends_count":2032,"profile_image_url_https":"https://pbs.twimg.com/profile_images/866777657022828544/reAKQA5E_normal.jpg","listed_count":45,"profile_background_image_url":"http://pbs.twimg.com/profile_background_images/215390987/montagem.jpg","default_profile_image":false,"favourites_count":873,"description":"draco dormiens nunquam titillandus\ninstagram: @leonypacheco","created_at":"Wed Aug 05 01:08:12 +0000 2009","is_translator":false,"profile_background_image_url_https":"https://pbs.twimg.com/profile_background_images/215390987/montagem.jpg","protected":false,"screen_name":"leonypacheco","id_str":"62986843","profile_link_color":"0084B4","is_translation_enabled":false,"translator_type":"none","id":62986843,"geo_enabled":false,"profile_background_color":"C0DEED","lang":"pt","has_extended_profile":false,"profile_sidebar_border_color":"C0DEED","profile_text_color":"333333","verified":false,"profile_image_url":"http://pbs.twimg.com/profile_images/866777657022828544/reAKQA5E_normal.jpg","time_zone":"Brasilia","url":null,"contributors_enabled":false,"profile_background_tile":true,"profile_banner_url":"https://pbs.twimg.com/profile_banners/62986843/1408208914","entities":{"description":{"urls":[]}},"statuses_count":10026,"follow_request_sent":false,"followers_count":2046,"profile_use_background_image":true,"default_profile":false,"following":false,"name":"Lê","location":"Pindamonhangaba","profile_sidebar_fill_color":"DDEEF6","notifications":false}},"retweet_count":12,"retweeted":false,"geo":null,"in_reply_to_screen_name":null,"is_quote_status":false,"id_str":"933307031028686851","in_reply_to_user_id":null,"favorite_count":0,"id":933307031028686851,"text":"RT @leonypacheco: Tenho gostos peculiares que pessoas normais não entenderiam...\n\n#ConteUmSegredoSeu https://t.co/K7fVqBIoNP","place":null,"lang":"pt","favorited":false,"possibly_sensitive":false,"coordinates":null,"truncated":false,"entities":{"urls":[],"hashtags":[{"indices":[82,100],"text":"ConteUmSegredoSeu"}],"media":[{"display_url":"pic.twitter.com/K7fVqBIoNP","source_user_id":62986843,"type":"photo","media_url":"http://pbs.twimg.com/media/DPO7a_YXUAAvxFA.jpg","source_status_id":933295636509876226,"url":"https://t.co/K7fVqBIoNP","indices":[101,124],"sizes":{"small":{"w":680,"h":679,"resize":"fit"},"large":{"w":1079,"h":1078,"resize":"fit"},"thumb":{"w":150,"h":150,"resize":"crop"},"medium":{"w":1079,"h":1078,"resize":"fit"}},"id_str":"933295620160442368","expanded_url":"https://twitter.com/leonypacheco/status/933295636509876226/photo/1","source_status_id_str":"933295636509876226","media_url_https":"https://pbs.twimg.com/media/DPO7a_YXUAAvxFA.jpg","id":933295620160442368,"source_user_id_str":"62986843"}],"user_mentions":[{"indices":[3,16],"screen_name":"leonypacheco","id_str":"62986843","name":"Lê","id":62986843}],"symbols":[]},"contributors":null,"user":{"utc_offset":-7200,"friends_count":5687,"profile_image_url_https":"https://pbs.twimg.com/profile_images/930416349469446144/AoBsIbI__normal.jpg","listed_count":24,"profile_background_image_url":"http://pbs.twimg.com/profile_background_images/689773106601312256/fAzjBrZy.jpg","default_profile_image":false,"favourites_count":3224,"description":"《BT 2013 ☆ PWT 2017》| #엑소","created_at":"Sun Jun 30 00:03:15 +0000 2013","is_translator":false,"profile_background_image_url_https":"https://pbs.twimg.com/profile_background_images/689773106601312256/fAzjBrZy.jpg","protected":false,"screen_name":"biebsuicidie","id_str":"1556823115","profile_link_color":"708090","is_translation_enabled":false,"translator_type":"none","id":1556823115,"geo_enabled":true,"profile_background_color":"FFFFFF","lang":"pt","has_extended_profile":true,"profile_sidebar_border_color":"FFFFFF","profile_text_color":"333333","verified":false,"profile_image_url":"http://pbs.twimg.com/profile_images/930416349469446144/AoBsIbI__normal.jpg","time_zone":"Brasilia","url":null,"contributors_enabled":false,"profile_background_tile":false,"profile_banner_url":"https://pbs.twimg.com/profile_banners/1556823115/1507073557","entities":{"description":{"urls":[]}},"statuses_count":96074,"follow_request_sent":false,"followers_count":11296,"profile_use_background_image":true,"default_profile":false,"following":false,"name":"joyce","location":"um dia no exoplanet outro em neverland","profile_sidebar_fill_color":"DDEEF6","notifications":false}}